Workbook

Sheet Funding conclusion
A2: Eli Lilly and Company funding conclusion
A3: Balance sheet 2026-06-30. Interpretation checked 2026-10-16. Source dates remain historical.
A5: Question | B5: Checked interpretation
A6: Conclusion | B6: Acquisition and manufacturing spending compete with repayment resources. H1 cash generation after cash PP&E was less than acquisition/IPR&D cash plus shareholder payouts. Incomplete payment dates and unverified post-expiry credit prevent a future funding-surplus conclusion.
A7: Near-term obligations | B7: At June 30, 2026, current borrowing was $7.050B, a carrying classification without a complete dated principal schedule. Unpaid acquisition cash was $296M with dates unstated. Approximately $2.8B for pending AtaiBeckley was conditional on closing, disclosed August 5.
A8: Resources and access | B8: $8.950B cash at June 30 excludes restricted cash. H1 2026 OCF less cash PP&E was $10.764B, already reflected in cash. June unused commitments of $10.1B are not verified drawable funds. The $6B facility's August 2026 expiry has no checked renewal.
A9: Competing cash uses | B9: H1 2026 acquisitions/IPR&D used $13.291B and dividends/buybacks $7.051B, while net borrowing contributed $12.602B. July acquisitions used approximately $2B. August's $4.5B Indiana announcement has no cash schedule. Subsequent uses do not establish an updated cash balance.
A10: Decisive unknowns | B10: Future funding coverage: Unavailable. Needed: remaining principal dates, current drawable credit and acquisition/manufacturing payment timing. The December 2025 supply/manufacturing ceiling of up to approximately $10B is conditional over generally up to eight years. Its overlap with later investment announcements is unresolved.
A12: Historical interest coverage | B12: Multiple; historical accrual earnings / interest, not repayment coverage
A13: TTM coverage (x) | B13: =IF(ISNUMBER('Debt and liquidity'!B50),'Debt and liquidity'!B50,NA()) -> 31.170528
A14: Company-specific basis | B14: TTM Jul 2025–Jun 2026: derived operating income $33.633B / reported interest $1.079B. Annual interest is net of capitalization; the interim basis and capitalized amount are unstated. No capitalization adjustment or earnings addback is made.
A15: Interpretation across companies | B15: Coverage bases differ: Lilly derives operating income and its interim capitalization basis is unstated. Oracle uses reported operating income and a reported interest line with unresolved composition/capitalization. Vistra uses reported operating income and a separate interest component before the capitalized-interest deduction. The periods also differ. These historical accrual ratios do not rank funding strength, measure covenant headroom or prove future repayment capacity.
A17: Future funding coverage | B17: Unavailable: payment timing, accessible resources and future cash generation are not jointly established.
A18: Source interpretation | B18: Narrative reflects the checked source snapshot. Editing workbook inputs updates calculations but requires a new review of the narrative.
A20: Workbook contents — select the named tab | B20: Question / evidence
A21: Funding conclusion | B21: Start here: obligations, accessible resources, competing uses and decisive unknowns.
A22: Borrowing and leases | B22: Borrowing components, dated lease liabilities and uncommenced commitments, separately.
A23: Debt and liquidity | B23: Latest checked ratios, formulas, periods and company-specific limits.
A24: History | B24: Annual versus latest dated balances; overlapping FY and TTM flows. Unavailable is not zero.
A25: Annual history | B25: Five completed fiscal years, sourced inputs and FCF formulas; annual history is separate from the latest TTM.
A26: Core charts | B26: What remained after capital spending, and how checked cash/borrowing balances changed.
A27: Repayment review | B27: H1 cash uses, conditional commitments, credit evidence and selected May issuance maturities.
... A34: Reading the charts | B34: FCF is OCF less capex, not another cash flow. Annual charts and the latest TTM keep their own periods and bases.

Sheet Borrowing and leases
A2: Eli Lilly and Company borrowing and leases
A3: Amounts in USD millions. Each balance retains its own date. Baseline borrowing excludes leases.
A5: Borrowing component | B5: USD millions | C5: As of | D5: Source / filing | E5: Basis
A6: Current borrowing | B6: =IF(ISNUMBER('Data'!B120),'Data'!B120,NA()) -> 7050000000 | C6: 2026-06-30T00:00:00.000Z | D6: 10-Q balance sheet, p. 7; filed 2026-08-05 | E6: Short-term borrowings and current maturities of long-term debt
A7: Noncurrent borrowing | B7: =IF(ISNUMBER('Data'!B121),'Data'!B121,NA()) -> 47858000000 | C7: 2026-06-30T00:00:00.000Z | D7: 10-Q balance sheet, p. 7; filed 2026-08-05 | E7: Long-term debt
A8: Baseline gross debt | B8: =SUM(B6:B7) -> 54908000000 | C8: 2026-06-30T00:00:00.000Z | D8: Derived from the components above | E8: Carrying amount; excludes leases.
A10: Borrowing scope | E10: Current borrowing includes short-term borrowings and current maturities. The Note 8 fair-value carrying amounts describe the same debt and are not added.
A13: Lease liability / commitment | B13: USD millions | C13: As of | D13: Source / filing | E13: Basis / Unavailable reason
A14: Lease liabilities at latest balance sheet | B14: Unavailable | C14: 2026-06-30T00:00:00.000Z | D14: Checked 10-Q review | E14: No lease liability amounts established in this 10-Q. Older amounts below are not substituted.
A15: Operating lease liabilities — current | B15: =IF(ISNUMBER('Data'!B123),'Data'!B123,NA()) -> 222000000 | C15: 2025-12-31T00:00:00.000Z | D15: 10-K Note 10, p. 76; filed 2026-02-12 | E15: Recognized lease liability; excluded from baseline borrowing.
A16: Operating lease liabilities — noncurrent | B16: =IF(ISNUMBER('Data'!B124),'Data'!B124,NA()) -> 1140000000 | C16: 2025-12-31T00:00:00.000Z | D16: 10-K Note 10, p. 76; filed 2026-02-12 | E16: Recognized lease liability; excluded from baseline borrowing.
A17: Operating lease liabilities — total | B17: =B15+B16 -> 1362000000 | C17: 2025-12-31T00:00:00.000Z | D17: 10-K Note 10, p. 76 | E17: Derived current + noncurrent; no separately tagged total.
A18: Finance lease liabilities | B18: Unavailable | C18: 2026-06-30T00:00:00.000Z | D18: 10-Q review; June amount not established | E18: No checked June amount. The 10-K describes operating leases only; finance leases are not reported, which is not zero.
A20: Leases not yet commenced | B20: Unavailable | C20: 2026-06-30T00:00:00.000Z | D20: Saved pilot evidence; 10-Q review | E20: No checked amount for leases not yet commenced is established in the saved pilot evidence. Unavailable does not mean zero.

Sheet Debt and liquidity
A2: Eli Lilly and Company
A3: Balance sheet June 30, 2026. TTM July 2025–June 2026. USD millions unless ratio or %.
A5: Measure | B5: Value (USD millions / x / %) | C5: Period end | D5: Formula / basis / limitation
A6: Cash and cash equivalents | B6: =IF(ISNUMBER('Data'!B2),'Data'!B2,NA()) -> 8950000000 | C6: 2026-06-30T00:00:00.000Z | D6: Cash and cash equivalents excluding restricted cash. Investments are not substituted.
A7: Baseline gross debt | B7: =IF(AND(IF(ISNUMBER('Data'!B3),'Data'!B3,NA())>=0,IF(ISNUMBER('Data'!B4),'Data'!B4,NA())>=0),IF(ISNUMBER('Data'!B3),'Data'!B3,NA())+IF(ISNUMBER('Data'!B4),'Data'!B4,NA()),NA()) -> 54908000000 | C7: 2026-06-30T00:00:00.000Z | D7: Carrying amount of borrowing. Operating/finance leases and commitments are excluded. In this 10-Q, the Note 8 fair-value table's carrying amounts (commercial paper 5,284M plus long-term debt including current portion 49,624M) present the same 54,908M; they are not added.
A8: Net debt | B8: =B7-B6 -> 45958000000 | C8: 2026-06-30T00:00:00.000Z | D8: Baseline borrowing less cash excluding restricted cash. Same date and filing. Negative net debt is retained.
A9: Current ratio | B9: =IF(IF(ISNUMBER('Data'!B5),'Data'!B5,NA())>0,IF(ISNUMBER('Data'!B6),'Data'!B6,NA())/IF(ISNUMBER('Data'!B5),'Data'!B5,NA()),NA()) -> 1.3546428 | C9: 2026-06-30T00:00:00.000Z | D9: Total current assets / total current liabilities from one balance sheet. Liabilities include more than borrowing; assets include more than cash.
A10: Operating cash flow | B10: =(1*IF(ISNUMBER('Data'!B7),'Data'!B7,NA()))+(1*IF(ISNUMBER('Data'!B8),'Data'!B8,NA()))+(-1*IF(ISNUMBER('Data'!B9),'Data'!B9,NA())) -> 28083000000 | C10: 2026-06-30T00:00:00.000Z | D10: Reported historical OCF; recurrence is not established. Uses FY + current YTD - prior YTD.
A11: Purchases of property and equipment | B11: =(1*IF(ISNUMBER('Data'!B10),'Data'!B10,NA()))+(1*IF(ISNUMBER('Data'!B11),'Data'!B11,NA()))+(-1*IF(ISNUMBER('Data'!B12),'Data'!B12,NA())) -> 9893000000 | C11: 2026-06-30T00:00:00.000Z | D11: Reported purchases of property and equipment; excludes acquisitions and other investing cash flows.
A12: Free cash flow | B12: =B10-B11 -> 18190000000 | C12: 2026-06-30T00:00:00.000Z | D12: OCF less reported capital spending. Uses the spending basis above; excludes acquisitions, dividends and other cash uses.
A13: Operating cash flow / debt | B13: =IF(B7>0,B10/B7,NA()) -> 0.51145553 | C13: 2026-06-30T00:00:00.000Z | D13: Historical TTM OCF / period-end baseline borrowing, not average debt or repayment coverage. The reported OCF basis above is retained.
A14: Free cash flow / debt | B14: =IF(B7>0,B12/B7,NA()) -> 0.33128142 | C14: 2026-06-30T00:00:00.000Z | D14: Historical TTM FCF / period-end baseline borrowing. Uses the spending basis above; not repayment coverage.
A15: Historical interest coverage | B15: =B50 -> 31.170528 | C15: 2026-06-30T00:00:00.000Z | D15: FY2025 Note 11 explicitly reports interest on borrowings net of capitalized interest. The interim segment table labels the line interest expense without explicitly stating its capitalization basis. All three amounts are used as reported, before any interest-income offset. Capitalized interest is not added or subtracted; its amount and total interest incurred are Unavailable. See the detailed interest build for composition and limitations.
A17: Selected obligations, separate from borrowing
A18: Item | B18: Disclosed amount / timing | C18: Basis
A19: ='Data'!A16 -> Pending AtaiBeckley acquisition | B19: ='Data'!B16 -> Approximately $2.8B | C19: ='Data'!I16 -> Potential payment at closing, subject to closing conditions. Not recognized as borrowing.
A20: ='Data'!A17 -> Venture fund commitments | B20: ='Data'!B17 -> Approximately $806M | C20: ='Data'!I17 -> Expected to be paid over up to ten years. Not recognized as borrowing.
A23: Remaining gaps
A24: June lease liabilities and a complete updated principal schedule are Unavailable. Historical interest coverage is built below.
A25: See Repayment review for dated cash flows, facilities, acquisitions and manufacturing commitments.
A26: Financing index checked through October 15, 2026. See Repayment review for May terms; all sources and limits are in Data.
A30: Historical operating-income interest coverage
A31: TTM July 1, 2025–June 30, 2026. Derived operating income / reported interest expense on borrowings. USD millions unless ratio.
A33: Calculation component | B33: FY2025 | C33: + H1 2026 | D33: − H1 2025
A34: Revenue | B34: =IF(ISNUMBER('Data'!B68),'Data'!B68,NA()) -> 65179000000 | C34: =IF(ISNUMBER('Data'!B77),'Data'!B77,NA()) -> 42773000000 | D34: =IF(ISNUMBER('Data'!B86),'Data'!B86,NA()) -> 28286000000
A35: Cost of sales | B35: =IF(ISNUMBER('Data'!B69),'Data'!B69,NA()) -> 11052000000 | C35: =IF(ISNUMBER('Data'!B78),'Data'!B78,NA()) -> 6845000000 | D35: =IF(ISNUMBER('Data'!B87),'Data'!B87,NA()) -> 4672000000
A36: R&D | B36: =IF(ISNUMBER('Data'!B70),'Data'!B70,NA()) -> 13337000000 | C36: =IF(ISNUMBER('Data'!B79),'Data'!B79,NA()) -> 7329000000 | D36: =IF(ISNUMBER('Data'!B88),'Data'!B88,NA()) -> 6070000000
A37: SG&A | B37: =IF(ISNUMBER('Data'!B71),'Data'!B71,NA()) -> 11094000000 | C37: =IF(ISNUMBER('Data'!B80),'Data'!B80,NA()) -> 6364000000 | D37: =IF(ISNUMBER('Data'!B89),'Data'!B89,NA()) -> 5221000000
A38: Acquired IPR&D, expense | B38: =IF(ISNUMBER('Data'!B72),'Data'!B72,NA()) -> 2910000000 | C38: =IF(ISNUMBER('Data'!B81),'Data'!B81,NA()) -> 3360000000 | D38: =IF(ISNUMBER('Data'!B90),'Data'!B90,NA()) -> 1726000000
A39: Impairment, restructuring and special charges | B39: =IF(ISNUMBER('Data'!B73),'Data'!B73,NA()) -> 484000000 | C39: =IF(ISNUMBER('Data'!B82),'Data'!B82,NA()) -> 982000000 | D39: =IF(ISNUMBER('Data'!B91),'Data'!B91,NA()) -> 35000000
A40: Derived operating income | B40: =B34-SUM(B35:B39) -> 26302000000 | C40: =C34-SUM(C35:C39) -> 17893000000 | D40: =D34-SUM(D35:D39) -> 10562000000
A41: Pretax income, reported | B41: =IF(ISNUMBER('Data'!B75),'Data'!B75,NA()) -> 25731000000 | C41: =IF(ISNUMBER('Data'!B84),'Data'!B84,NA()) -> 18097000000 | D41: =IF(ISNUMBER('Data'!B93),'Data'!B93,NA()) -> 10233000000
A42: Nonoperating income (expense), tagged sign | B42: =IF(ISNUMBER('Data'!B74),'Data'!B74,NA()) -> -571000000 | C42: =IF(ISNUMBER('Data'!B83),'Data'!B83,NA()) -> 204000000 | D42: =IF(ISNUMBER('Data'!B92),'Data'!B92,NA()) -> -329000000
A43: Control: pretax − tagged nonoperating | B43: =B41-B42 -> 26302000000 | C43: =C41-C42 -> 17893000000 | D43: =D41-D42 -> 10562000000
A44: Reconciliation difference, zero = matched | B44: =B40-B43 -> 0 | C44: =C40-C43 -> 0 | D44: =D40-D43 -> 0
A46: Reported interest expense on borrowings | B46: =IF(ISNUMBER('Data'!B76),'Data'!B76,NA()) -> 895000000 | C46: =IF(ISNUMBER('Data'!B85),'Data'!B85,NA()) -> 677000000 | D46: =IF(ISNUMBER('Data'!B94),'Data'!B94,NA()) -> 493000000
A48: TTM derived operating income | B48: =B40+C40-D40 -> 33633000000 | C48: FY + current H1 − prior H1 | D48: Acquired IPR&D and special charges are retained; no adjusted earnings addbacks.
A49: TTM reported interest expense | B49: =B46+C46-D46 -> 1079000000 | C49: FY + current H1 − prior H1 | D49: Annual 895 + H1 2026 677 − H1 2025 493. No capitalized-interest adjustment or interest-income offset.
A50: Historical interest coverage | B50: =IF(AND(B44=0,C44=0,D44=0,B49>0),B48/B49,NA()) -> 31.170528 | C50: Operating income / interest | D50: Accrual earnings measure. Not cash interest coverage, covenant headroom, drawable credit or a repayment forecast.
A52: FY2025 Note 11 explicitly reports interest on borrowings net of capitalized interest. The interim segment table labels the line interest expense without explicitly stating its capitalization basis. All three amounts are used as reported, before any interest-income offset. Capitalized interest is not added or subtracted; its amount and total interest incurred are Unavailable.
A53: Historical accrual-based earnings coverage, not cash interest coverage, a repayment forecast, a covenant calculation or proof of drawable credit. Operating income is derived, not a reported Lilly subtotal. Acquired IPR&D and impairment/restructuring charges remain included; no adjusted earnings addbacks. Interim capitalization basis and future interest are not inferred.
A54: Operating income is derived, not a reported subtotal. Statement-table selection excludes rounded MD&A repeats. Other–net XBRL values are positive income / negative expense; the control preserves and subtracts that sign.
A55: Interest uses the exact six-month single-segment contexts in the quarterly filing; three-month amounts are not added. Source tags, dates, dimensions and selection rules are in Data.

Sheet History
A2: Eli Lilly and Company — dated history
A3: USD millions, except ratios (x) and percentages (%). Fiscal year and later TTM both span twelve months and overlap.
A5: Measure | B5: As of / FY ended 2025-12-31 | C5: As of / TTM ended 2026-06-30 | D5: Basis / limits
A6: Cash and cash equivalents | B6: =IF(ISNUMBER('Data'!B130),'Data'!B130,NA()) -> 7268000000 | C6: ='Debt and liquidity'!B6 -> 8950000000 | D6: Cash and cash equivalents excluding restricted cash. Investments are not substituted.
A7: Baseline gross debt | B7: =IF(ISNUMBER('Data'!B133),'Data'!B133,NA())+IF(ISNUMBER('Data'!B134),'Data'!B134,NA()) -> 42503000000 | C7: ='Debt and liquidity'!B7 -> 54908000000 | D7: Carrying borrowing; leases and commitments excluded. Latest column only: In this 10-Q, the Note 8 fair-value table's carrying amounts (commercial paper 5,284M plus long-term debt including current portion 49,624M) present the same 54,908M; they are not added.
A8: Net debt | B8: =B7-B6 -> 35235000000 | C8: ='Debt and liquidity'!B8 -> 45958000000 | D8: Baseline borrowing less cash excluding restricted cash. Same date and filing. Negative net debt is retained.
A9: Current ratio | B9: =IF(IF(ISNUMBER('Data'!B132),'Data'!B132,NA())>0,IF(ISNUMBER('Data'!B131),'Data'!B131,NA())/IF(ISNUMBER('Data'!B132),'Data'!B132,NA()),NA()) -> 1.5791132 | C9: ='Debt and liquidity'!B9 -> 1.3546428 | D9: Total current assets / total current liabilities from one balance sheet. Liabilities include more than borrowing; assets include more than cash.
A10: Operating cash flow | B10: =IF(ISNUMBER('Data'!B135),'Data'!B135,NA()) -> 16813000000 | C10: ='Debt and liquidity'!B10 -> 28083000000 | D10: Annual column: reported fiscal-year OCF. Latest column only: Reported historical OCF; recurrence is not established. Uses FY + current YTD - prior YTD.
A11: Purchases of property and equipment | B11: =IF(ISNUMBER('Data'!B136),'Data'!B136,NA()) -> 7841000000 | C11: ='Debt and liquidity'!B11 -> 9893000000 | D11: Reported purchases of property and equipment; excludes acquisitions and other investing cash flows.
A12: Free cash flow | B12: =B10-B11 -> 8972000000 | C12: ='Debt and liquidity'!B12 -> 18190000000 | D12: OCF less reported capital spending. Uses the spending basis above; excludes acquisitions, dividends and other cash uses.
A13: Operating cash flow / debt | B13: =IF(B7>0,B10/B7,NA()) -> 0.39557208 | C13: ='Debt and liquidity'!B13 -> 0.51145553 | D13: Twelve-month flow / borrowing at each period end. Annual column uses FY; latest column uses TTM. Not repayment coverage.
A14: Free cash flow / debt | B14: =IF(B7>0,B12/B7,NA()) -> 0.21109098 | C14: ='Debt and liquidity'!B14 -> 0.33128142 | D14: Twelve-month flow / borrowing at each period end. Annual column uses FY; latest column uses TTM. Not repayment coverage.
A15: Historical interest coverage | B15: =IF(AND('Debt and liquidity'!B46>0,'Debt and liquidity'!B44=0),'Debt and liquidity'!B40/'Debt and liquidity'!B46,NA()) -> 29.387709 | C15: ='Debt and liquidity'!B15 -> 31.170528 | D15: Annual interest is reported net of capitalized interest; the later TTM includes interim expense whose capitalization basis is unstated. Amounts remain as reported.
A17: Period definitions | D17: Balance-sheet figures compare the stated dates. Flows and interest coverage compare a fiscal year with a later TTM: both span twelve months and overlap. No interim annualization, independent-period growth rate or future repayment coverage is inferred.
A18: Fiscal-year flows | D18: 2025-01-01 to 2025-12-31
A19: Later TTM flows | D19: 2025-07-01 to 2026-06-30

Sheet Annual history
A2: LLY — five completed fiscal years
A3: USD millions. Full fiscal years; latest TTM remains separate.
A4: Fiscal year end | B4: 2021-12-31T00:00:00.000Z | C4: 2022-12-31T00:00:00.000Z | D4: 2023-12-31T00:00:00.000Z | E4: 2024-12-31T00:00:00.000Z | F4: 2025-12-31T00:00:00.000Z
A5: Measure | B5: FY2021 | C5: FY2022 | D5: FY2023 | E5: FY2024 | F5: FY2025
A6: Cash and equivalents | B6: =IF(ISNUMBER('Data'!B140),'Data'!B140,NA()) -> 3818500000 | C6: =IF(ISNUMBER('Data'!B145),'Data'!B145,NA()) -> 2067000000 | D6: =IF(ISNUMBER('Data'!B150),'Data'!B150,NA()) -> 2818600000 | E6: =IF(ISNUMBER('Data'!B155),'Data'!B155,NA()) -> 3268400000 | F6: =IF(ISNUMBER('Data'!B160),'Data'!B160,NA()) -> 7268000000
A7: Baseline borrowing | B7: =IF(ISNUMBER('Data'!B141),'Data'!B141,NA())+IF(ISNUMBER('Data'!B142),'Data'!B142,NA()) -> 16884700000 | C7: =IF(ISNUMBER('Data'!B146),'Data'!B146,NA())+IF(ISNUMBER('Data'!B147),'Data'!B147,NA()) -> 16238600000 | D7: =IF(ISNUMBER('Data'!B151),'Data'!B151,NA())+IF(ISNUMBER('Data'!B152),'Data'!B152,NA()) -> 25225300000 | E7: =IF(ISNUMBER('Data'!B156),'Data'!B156,NA())+IF(ISNUMBER('Data'!B157),'Data'!B157,NA()) -> 33644200000 | F7: =IF(ISNUMBER('Data'!B161),'Data'!B161,NA())+IF(ISNUMBER('Data'!B162),'Data'!B162,NA()) -> 42503000000
A8: Operating cash flow | B8: =IF(ISNUMBER('Data'!B143),'Data'!B143,NA()) -> 7365900000 | C8: =IF(ISNUMBER('Data'!B148),'Data'!B148,NA()) -> 7585700000 | D8: =IF(ISNUMBER('Data'!B153),'Data'!B153,NA()) -> 4240100000 | E8: =IF(ISNUMBER('Data'!B158),'Data'!B158,NA()) -> 8817900000 | F8: =IF(ISNUMBER('Data'!B163),'Data'!B163,NA()) -> 16813000000
A9: Capital spending | B9: =IF(ISNUMBER('Data'!B144),'Data'!B144,NA()) -> 1309800000 | C9: =IF(ISNUMBER('Data'!B149),'Data'!B149,NA()) -> 1854300000 | D9: =IF(ISNUMBER('Data'!B154),'Data'!B154,NA()) -> 3447600000 | E9: =IF(ISNUMBER('Data'!B159),'Data'!B159,NA()) -> 5057800000 | F9: =IF(ISNUMBER('Data'!B164),'Data'!B164,NA()) -> 7841000000
A10: Free cash flow | B10: =B8-B9 -> 6056100000 | C10: =C8-C9 -> 5731400000 | D10: =D8-D9 -> 792500000 | E10: =E8-E9 -> 3760100000 | F10: =F8-F9 -> 8972000000
A12: Annual basis | B12: Annual cash and borrowing are fiscal-year-end balances. OCF and capital spending cover each full fiscal
B13: year. FCF = OCF − capital spending; it excludes acquisitions and other investing and financing uses.
B14: Historical amounts do not establish future repayment coverage. Fiscal calendars, business perimeters and
B15: capital-spending definitions differ.
A17: Presentation choice | B17: 2021/2022 cash flows use FY2023’s disclosed IPR&D milestone reclassification. OCF increased by
B18: $105.2M/$501.3M through classification, not new cash generation. Cash and borrowing retain their original
B19: balance sheets. FCF does not deduct IPR&D purchases.

Sheet Core charts
A2: LLY — two chart questions
A3: TTM 2025-07-01 to 2026-06-30. Values stored in USD, displayed in millions.
A5: TTM measure | B5: USD millions
A6: Operating cash flow | B6: ='Debt and liquidity'!B10 -> 28083000000
A7: Capital spending | B7: =-'Debt and liquidity'!B11 -> -9893000000
A8: Free cash flow | B8: ='Debt and liquidity'!B12 -> 18190000000
A10: Calculation basis | D10: FCF = OCF − capital spending. FCF is a result, not an additional cash flow. Capital spending is shown negative.
A24: Balance-sheet date | B24: Cash and equivalents | C24: Baseline borrowing
A25: 2025-12-31 | B25: ='History'!B6 -> 7268000000 | C25: ='History'!B7 -> 42503000000
A26: 2026-06-30 | B26: ='History'!C6 -> 8950000000 | C26: ='History'!C7 -> 54908000000
A29: Scope / missing history | D29: Baseline borrowing excludes leases; cash excludes restricted cash and investments. These balances do not establish repayment coverage.
A41: Evidence trail | D41: Chart values link to Debt and liquidity and History. Data retains the exact input periods, tags, accessions and source URLs.

Sheet Repayment review
A2: Lilly — dated liquidity and repayment review
A3: Saved filings reviewed October 15, 2026. Cash flows: January–June 2026. USD millions.
A4: H1 cash generation after PP&E was positive; acquisitions and payouts competed for it. Net borrowing contributed to cash growth. Future funding coverage: Unavailable.
A6: Half-year cash build | B6: USD millions | C6: Period / basis | D6: Interpretation
A7: Opening cash | B7: =IF(ISNUMBER('Data'!B37),'Data'!B37,NA()) -> 7268000000 | C7: December 31, 2025 | D7: Excludes restricted cash. Not an additional half-year flow.
A8: Operating cash flow | B8: =IF(ISNUMBER('Data'!B21),'Data'!B21,NA()) -> 16023000000 | C8: January–June 2026 | D8: Historical; includes working capital. Future recurrence not established.
A9: Cash PP&E spending | B9: =-IF(ISNUMBER('Data'!B22),'Data'!B22,NA()) -> -5259000000 | C9: January–June 2026 | D9: Cash use, not a forecast of manufacturing investment.
A10: Cash acquisitions, net of cash acquired | B10: =-IF(ISNUMBER('Data'!B25),'Data'!B25,NA()) -> -9805000000 | C10: January–June 2026 | D10: Not added again to the approximately $13.3B business-development disclosure.
A11: Purchased in-process R&D | B11: =-IF(ISNUMBER('Data'!B24),'Data'!B24,NA()) -> -3486000000 | C11: January–June 2026 | D11: Separate cash use; not all acquisition-related expense is cash.
A12: Cash dividends | B12: =-IF(ISNUMBER('Data'!B28),'Data'!B28,NA()) -> -3094000000 | C12: January–June 2026 | D12: Competes with repayments for cash.
A13: Share repurchases | B13: =-IF(ISNUMBER('Data'!B32),'Data'!B32,NA()) -> -3957000000 | C13: January–June 2026 | D13: Historical spending; no future pace assumed.
A14: Short-term borrowing, net | B14: =IF(ISNUMBER('Data'!B29),'Data'!B29,NA()) -> 5284000000 | C14: January–June 2026 | D14: Financing inflow, not recurring operating generation.
A15: Long-term debt proceeds, net | B15: =IF(ISNUMBER('Data'!B30),'Data'!B30,NA()) -> 8941000000 | C15: January–June 2026 | D15: May $9B issue is already included here; net cash differs from face amount.
A16: Long-term debt repaid | B16: =-IF(ISNUMBER('Data'!B31),'Data'!B31,NA()) -> -1623000000 | C16: January–June 2026 | D16: Already paid; not a future maturity schedule.
A17: Other investing and financing | B17: =-IF(ISNUMBER('Data'!B23),'Data'!B23,NA())-IF(ISNUMBER('Data'!B26),'Data'!B26,NA())+IF(ISNUMBER('Data'!B33),'Data'!B33,NA()) -> -1357000000 | C17: January–June 2026 | D17: Investment purchases, other investing and other financing.
A18: Exchange-rate effect | B18: =IF(ISNUMBER('Data'!B35),'Data'!B35,NA()) -> 15000000 | C18: January–June 2026 | D18: Reconciles the cash balance.
A19: Calculated cash change | B19: =SUM(B8:B18) -> 1682000000 | C19: January–June 2026 | D19: All signed flows counted once.
A20: Calculated closing cash | B20: =B7+B19 -> 8950000000 | C20: June 30, 2026 | D20: Opening cash plus change.
A21: Reported closing cash | B21: =IF(ISNUMBER('Data'!B38),'Data'!B38,NA()) -> 8950000000 | C21: June 30, 2026 | D21: Not a current cash balance after subsequent payments.
A22: Cash reconciliation difference | B22: =B20-B21 -> 0 | C22: Zero = reconciled | D22: No cash forecast or unrestricted-funding total.
A23: OCF less cash PP&E spending | B23: =B8+B9 -> 10764000000 | C23: Historical H1 only | D23: Excludes acquisitions, payouts and other cash uses.
A24: Net borrowing cash flow | B24: =SUM(B14:B16) -> 12602000000 | C24: Historical H1 only | D24: Borrowing contributed to closing cash.
A25: Acquisitions + purchased IPR&D | B25: =-SUM(B10:B11) -> 13291000000 | C25: Historical H1 only | D25: Approximately $13.3B, already spent.
A26: Dividends + buybacks | B26: =-SUM(B12:B13) -> 7051000000 | C26: Historical H1 only | D26: Not automatically recurring future obligations.
F27: H1 cash contribution | G27: USD millions
F28: Operating cash flow | G28: =B8 -> 16023000000
A29: Credit capacity, dates kept separate | B29: USD millions | C29: Date / expiry | D29: Availability limitation | F29: Cash PP&E spending | G29: =B9 -> -5259000000
A30: Unused committed facilities | B30: =IF(ISNUMBER('Data'!B58),'Data'!B58,NA()) -> 10100000000 | C30: June 30, 2026 | D30: Reported unused, not cash or verified drawable. $10B supports CP and is not added again. | F30: Acquisitions + purchased IPR&D | G30: =-B25 -> -13291000000
A31: 364-day facility expires August 2026 | B31: =IF(ISNUMBER('Data'!B56),'Data'!B56,NA()) -> 6000000000 | C31: August 2026 expiry | D31: Annual terms: 364-day facility. Exact expiry day and renewal Unavailable; do not carry June capacity past expiry. | F31: Dividends + buybacks | G31: =-B26 -> -7051000000
A32: Facility expires December 2029 | B32: =IF(ISNUMBER('Data'!B57),'Data'!B57,NA()) -> 4000000000 | C32: December 2029 expiry | D32: Annual terms only. Exact day, June facility composition, contract conditions and current draws Unavailable. | F32: Net borrowing | G32: =B24 -> 12602000000
F33: Other cash flows including FX | G33: =B17+B18 -> -1342000000
A34: Drawable credit | B34: Unavailable | C34: No saved credit agreement | D34: Draw conditions, covenants, permitted uses and post-August renewal not established. Cash + commitments is not a verified funding total.
A35: December unused capacity | B35: =IF(ISNUMBER('Data'!B55),'Data'!B55,NA()) -> 10100000000 | C35: December 31, 2025 | D35: Annual unused total is $10.1B, primarily the $6B and $4B facilities. The residual $0.1B is not separately described.
A38: Acquisitions / manufacturing | B38: USD millions | C38: Date and classification | D38: Timing, overlap and funding limitation
A39: Pending AtaiBeckley acquisition | B39: =IF(ISNUMBER('Data'!B60),'Data'!B60,NA()) -> 2800000000 | C39: Disclosed August 5, 2026 · Approximate conditional closing payment | D39: Payable at closing, subject to conditions. Disclosed after quarter end; closing date, completion and funding allocation are not established here.
A40: Unpaid Kelonia cash consideration | B40: =IF(ISNUMBER('Data'!B61),'Data'!B61,NA()) -> 208000000 | C40: 2026-06-30 · Unpaid acquisition consideration | D40: Payment date Unavailable. Separate from cash already paid and from contingent-consideration fair value.
A41: Unpaid Centessa cash consideration | B41: =IF(ISNUMBER('Data'!B62),'Data'!B62,NA()) -> 88000000 | C41: 2026-06-30 · Unpaid acquisition consideration | D41: Payment date Unavailable. Do not add to paid acquisition cash or contingent-consideration fair value.
A42: July infectious-disease acquisitions: cash paid | B42: =IF(ISNUMBER('Data'!B63),'Data'!B63,NA()) -> 2000000000 | C42: July 2026 · Approximate subsequent cash use | D42: Already paid after June. Other July cash flows are unknown; June cash less this payment is not a current cash balance.
A43: July acquisitions: aggregate consideration up to | B43: =IF(ISNUMBER('Data'!B64),'Data'!B64,NA()) -> 3900000000 | C43: July 2026 · Conditional aggregate ceiling | D43: Includes upfront cash and potential clinical, regulatory and commercial milestones. Includes the approximately $2B paid; do not add the two amounts or infer a precise remaining cash bill.
A44: Unfunded venture fund commitments | B44: =IF(ISNUMBER('Data'!B65),'Data'!B65,NA()) -> 806000000 | C44: 2026-06-30 · Approximate investment commitment | D44: Expected to be paid over up to ten years. Individual capital-call dates are Unavailable.
A45: Development-medicine supply arrangements: up to | B45: =IF(ISNUMBER('Data'!B66),'Data'!B66,NA()) -> 10000000000 | C45: 2025-12-31 · Approximate conditional purchase shortfall ceiling | D45: Payments if specified purchases are not met under executed manufacturing and supply agreements; durations generally up to eight years. Not an unconditional $10B bill. Updated June ceiling, annual payments and overlap with other spending are Unavailable.
A46: Additional Indiana manufacturing investment | B46: =IF(ISNUMBER('Data'!B67),'Data'!B67,NA()) -> 4500000000 | C46: Announced August 5, 2026 · Announced investment commitment | D46: Release says committed an additional $4.5B. Contractual payment schedule, spending to date and overlap with capex or supply commitments are not established by this release. Not added to debt or the $10B ceiling.
A48: Contingent consideration fair value | B48: =IF(ISNUMBER('Data'!B41),'Data'!B41,NA())+IF(ISNUMBER('Data'!B42),'Data'!B42,NA()) -> 2518000000 | C48: June 30, 2026 | D48: Current $814M + noncurrent $1,704M. Valuation, not dated payment or contractual maximum. Not added to acquisition amounts above.
A49: Future funding coverage | B49: Unavailable | C49: Each future obligation | D49: Future principal dates, future cash generation, payment dates and drawable credit not all established. No coverage ratio calculated.
A50: Scope | B50: Financing index through Oct 15, 2026 | C50: 10-K; 10-Q; earnings and financing documents | D50: SEC financing candidates screened through October 15. Not a complete review of all liability notes. No combined obligations total.
A53: Notes grouped by due year | B53: USD millions | C53: Basis date | D53: Interpretation
A54: Notes due 2026 | B54: =IF(ISNUMBER('Data'!B43),'Data'!B43,NA()) -> 1632000000 | C54: December 31, 2025 | D54: Historical carrying amount; not principal cash payments. Multi-year groups are combined.
A55: Notes due 2027 | B55: =IF(ISNUMBER('Data'!B44),'Data'!B44,NA()) -> 2516000000 | C55: December 31, 2025 | D55: Historical carrying amount; not principal cash payments. Multi-year groups are combined.
A56: Notes due 2028 | B56: =IF(ISNUMBER('Data'!B45),'Data'!B45,NA()) -> 3256000000 | C56: December 31, 2025 | D56: Historical carrying amount; not principal cash payments. Multi-year groups are combined.
A57: Notes due 2029 | B57: =IF(ISNUMBER('Data'!B46),'Data'!B46,NA()) -> 3077000000 | C57: December 31, 2025 | D57: Historical carrying amount; not principal cash payments. Multi-year groups are combined.
A58: Notes due 2030 | B58: =IF(ISNUMBER('Data'!B47),'Data'!B47,NA()) -> 2132000000 | C58: December 31, 2025 | D58: Historical carrying amount; not principal cash payments. Multi-year groups are combined.
A59: Notes due 2031–2040 | B59: =IF(ISNUMBER('Data'!B48),'Data'!B48,NA()) -> 11582000000 | C59: December 31, 2025 | D59: Historical carrying amount; not principal cash payments. Multi-year groups are combined.
A60: Notes due 2041–2050 | B60: =IF(ISNUMBER('Data'!B49),'Data'!B49,NA()) -> 4543000000 | C60: December 31, 2025 | D60: Historical carrying amount; not principal cash payments. Multi-year groups are combined.
A61: Notes due 2051–2060 | B61: =IF(ISNUMBER('Data'!B50),'Data'!B50,NA()) -> 8280000000 | C61: December 31, 2025 | D61: Historical carrying amount; not principal cash payments. Multi-year groups are combined.
A62: Notes due 2061–2070 | B62: =IF(ISNUMBER('Data'!B51),'Data'!B51,NA()) -> 5824000000 | C62: December 31, 2025 | D62: Historical carrying amount; not principal cash payments. Multi-year groups are combined.
A63: Total notes | B63: =SUM(B54:B62) -> 42842000000 | C63: December 31, 2025 | D63: Carrying amount; not payment total.
A64: Other debt and adjustments | B64: =-IF(ISNUMBER('Data'!B52),'Data'!B52,NA()) -> -339000000 | C64: December 31, 2025 | D64: Printed as (339). Tagged +339 source magnitude; presentation coefficient −1.
A65: Commercial paper | B65: =IF(ISNUMBER('Data'!B53),'Data'!B53,NA()) -> 0 | C65: December 31, 2025 | D65: Reported zero at December 31, 2025.
A66: Calculated total debt | B66: =SUM(B63:B65) -> 42503000000 | C66: December 31, 2025 | D66: Same annual filing; no roll-forward to June.
A67: Reported total debt | B67: =IF(ISNUMBER('Data'!B54),'Data'!B54,NA()) -> 42503000000 | C67: December 31, 2025 | D67: Reconciles to annual balance sheet.
A68: Debt reconciliation difference | B68: =B66-B67 -> 0 | C68: December 31, 2025 | D68: Zero = reconciled.
A70: June 30 principal schedule | B70: Unavailable | C70: Updated payment dates missing | D70: Do not allocate May issuance or H1 repayments to annual buckets. Current borrowing $7.050B is not an instrument-level schedule.
A71: Repayment conclusion | C71: Coverage Unavailable | D71: H1 cash generation after PP&E was positive; acquisitions and payouts competed for cash. Net borrowing contributed materially. Updated debt dates, draw terms/renewal and payment calendars are needed.
A74: May 2026 issue — documented stated maturities
A75: Initial issue principal, not a complete June/October outstanding-debt schedule. Already in June borrowing and H1 proceeds; do not add to either.
A76: Series | B76: Initial principal, USD millions | C76: Stated maturity | D76: Contract rate
A77: Floating 2028 | B77: =IF(ISNUMBER('Data'!B95),'Data'!B95,NA()) -> 750000000 | C77: ='Data'!E95 -> 46893 | D77: ="Compounded SOFR + "&TEXT('Data'!T95,"0.000%") -> Compounded SOFR + 0.350%
A78: Floating 2029 | B78: =IF(ISNUMBER('Data'!B96),'Data'!B96,NA()) -> 500000000 | C78: ='Data'!E96 -> 47258 | D78: ="Compounded SOFR + "&TEXT('Data'!T96,"0.000%") -> Compounded SOFR + 0.460%
A79: Fixed 2029 | B79: =IF(ISNUMBER('Data'!B97),'Data'!B97,NA()) -> 750000000 | C79: ='Data'!E97 -> 47258 | D79: ='Data'!S97 -> 0.0415
A80: Fixed 2031 | B80: =IF(ISNUMBER('Data'!B98),'Data'!B98,NA()) -> 1500000000 | C80: ='Data'!E98 -> 47988 | D80: ='Data'!S98 -> 0.04375
A81: Fixed 2033 | B81: =IF(ISNUMBER('Data'!B99),'Data'!B99,NA()) -> 1250000000 | C81: ='Data'!E99 -> 48719 | D81: ='Data'!S99 -> 0.0465
A82: Fixed 2036 | B82: =IF(ISNUMBER('Data'!B100),'Data'!B100,NA()) -> 1500000000 | C82: ='Data'!E100 -> 49815 | D82: ='Data'!S100 -> 0.0485
A83: Fixed 2056 | B83: =IF(ISNUMBER('Data'!B101),'Data'!B101,NA()) -> 1750000000 | C83: ='Data'!E101 -> 57120 | D83: ='Data'!S101 -> 0.056
A84: Fixed 2066 | B84: =IF(ISNUMBER('Data'!B102),'Data'!B102,NA()) -> 1000000000 | C84: ='Data'!E102 -> 60772 | D84: ='Data'!S102 -> 0.057
A85: Calculated initial issue total | B85: =SUM(B77:B84) -> 9000000000 | C85: May 20, 2026 | D85: Eight series; not additional June debt.
A86: Reported completed issue total | B86: =IF(ISNUMBER('Data'!B103),'Data'!B103,NA()) -> 9000000000 | C86: May 20, 2026 | D86: 8-K Item 8.01; face principal differs from net cash proceeds.
A87: Issue reconciliation difference | B87: =B85-B86 -> 0 | C87: Zero = reconciled | D87: No roll-forward to June outstanding principal.
A88: Current outstanding by series | B88: Unavailable | C88: June / October 2026 | D88: Initial issue amounts do not establish current balances.
A89: Drawable capacity / future coverage | B89: Unavailable | C89: October 15 review | D89: No new verified facility renewal, drawable credit or complete future funding coverage.
A91: The May 20 8-K's interest paragraph says 4.650% for the fixed 2029 notes, while its series title, final prospectus and Exhibit 4.3 clauses (i)/(v) agree on 4.150%. This review uses the corroborated contract rate, 4.150%, and retains the conflicting statement here.
A92: The May terms require 101% special redemption of specified series if the Centessa acquisition fails under the stated conditions. The terms cease to apply upon consummation; the June 10-Q Note 4 records acquisition on June 24, 2026. This resolved acquisition-failure condition is not presented as a future 101% cash bill. Optional redemptions and default acceleration remain possible; none is assumed.
A93: SEC submissions contain 1,001 filings, October 15, 2026 back to December 16, 2021; older pages end before the review period. All 2026 form rows were screened, prioritizing periodic reports, amendments, 8-Ks, shelf/prospectus/pricing filings and debt delisting. After June 30, the only 8-K is the saved August 5 earnings report; no later periodic report or amendment, 424B2 or FWP is listed. Ownership filings are not corporate financing capacity.
A94: The retrieved September 2025 10-Q describes the August 2025 renewal to $6B and extension of the $4B facility to December 2029. This is historical, not an August 2026 renewal. The annual and March/June reports and reviewed exhibit lists establish no current credit agreement or post-August 2026 renewal. No relevant bank agreement was identified in the reviewed SEC filing and exhibit references. Draw conditions, current usage, covenant headroom and actual drawable capacity remain Unavailable.
A95: Dates are stated contractual maturities, not calendar-adjusted payment forecasts. Indenture §1.11 and note-specific business-day provisions apply. Future interest amounts, floating-rate resets, actual early redemptions and cash available at maturity are not modeled.
A96: The June 2 Form 25 removes the 1.625% notes due 2026 from listing. It does not establish an instrument-level cash repayment amount and is not used to allocate H1 repayments.

Sheet Data
A1: Input | B1: USD millions | C1: Period start | D1: Period end | E1: Form | F1: Filed | G1: Accession | H1: Tag | I1: Context | J1: Scale | K1: Decimals | L1: Source | M1: Selection rule | N1: Unavailable reason | O1: Notes
A2: Cash and cash equivalents | B2: 8950000000 | D2: 2026-06-30T00:00:00.000Z | E2: 10-Q | F2: 2026-08-05T00:00:00.000Z | G2: 0000059478-26-000081 | H2: us-gaap:CashAndCashEquivalentsAtCarryingValue | L2: https://www.sec.gov/Archives/edgar/data/59478/000005947826000081/lly-20260630.htm | M2: USD instant at the balance-sheet date, from the latest original 10-K or 10-Q itself
A3: Short-term borrowings and current maturities of long-term debt | B3: 7050000000 | D3: 2026-06-30T00:00:00.000Z | E3: 10-Q | F3: 2026-08-05T00:00:00.000Z | G3: 0000059478-26-000081 | H3: us-gaap:DebtCurrent | L3: https://www.sec.gov/Archives/edgar/data/59478/000005947826000081/lly-20260630.htm | M3: USD instant at the balance-sheet date, from the latest original 10-K or 10-Q itself
A4: Long-term debt | B4: 47858000000 | D4: 2026-06-30T00:00:00.000Z | E4: 10-Q | F4: 2026-08-05T00:00:00.000Z | G4: 0000059478-26-000081 | H4: us-gaap:LongTermDebtNoncurrent | L4: https://www.sec.gov/Archives/edgar/data/59478/000005947826000081/lly-20260630.htm | M4: USD instant at the balance-sheet date, from the latest original 10-K or 10-Q itself
A5: Current liabilities | B5: 47741000000 | D5: 2026-06-30T00:00:00.000Z | E5: 10-Q | F5: 2026-08-05T00:00:00.000Z | G5: 0000059478-26-000081 | H5: us-gaap:LiabilitiesCurrent | L5: https://www.sec.gov/Archives/edgar/data/59478/000005947826000081/lly-20260630.htm | M5: USD instant at the balance-sheet date, from the latest original 10-K or 10-Q itself
A6: Current assets | B6: 64672000000 | D6: 2026-06-30T00:00:00.000Z | E6: 10-Q | F6: 2026-08-05T00:00:00.000Z | G6: 0000059478-26-000081 | H6: us-gaap:AssetsCurrent | L6: https://www.sec.gov/Archives/edgar/data/59478/000005947826000081/lly-20260630.htm | M6: USD instant at the balance-sheet date, from the latest original 10-K or 10-Q itself
A7: Operating cash flow · fiscal year | B7: 16813000000 | C7: 2025-01-01T00:00:00.000Z | D7: 2025-12-31T00:00:00.000Z | E7: 10-K | F7: 2026-02-12T00:00:00.000Z | G7: 0000059478-26-000013 | H7: us-gaap:NetCashProvidedByUsedInOperatingActivities | I7: c-1 | J7: 6 | K7: -6 | L7: https://www.sec.gov/Archives/edgar/data/59478/000005947826000013/lly-20251231.htm | M7: Exact tag, USD duration, exact start and end dates, no dimensions
A8: Operating cash flow · current year to date | B8: 16023000000 | C8: 2026-01-01T00:00:00.000Z | D8: 2026-06-30T00:00:00.000Z | E8: 10-Q | F8: 2026-08-05T00:00:00.000Z | G8: 0000059478-26-000081 | H8: us-gaap:NetCashProvidedByUsedInOperatingActivities | I8: c-1 | J8: 6 | K8: -6 | L8: https://www.sec.gov/Archives/edgar/data/59478/000005947826000081/lly-20260630.htm | M8: Exact tag, USD duration, exact start and end dates, no dimensions
A9: Operating cash flow · prior year to date | B9: 4753000000 | C9: 2025-01-01T00:00:00.000Z | D9: 2025-06-30T00:00:00.000Z | E9: 10-Q | F9: 2026-08-05T00:00:00.000Z | G9: 0000059478-26-000081 | H9: us-gaap:NetCashProvidedByUsedInOperatingActivities | I9: c-14 | J9: 6 | K9: -6 | L9: https://www.sec.gov/Archives/edgar/data/59478/000005947826000081/lly-20260630.htm | M9: Exact tag, USD duration, exact start and end dates, no dimensions
A10: Purchases of property and equipment · fiscal year | B10: 7841000000 | C10: 2025-01-01T00:00:00.000Z | D10: 2025-12-31T00:00:00.000Z | E10: 10-K | F10: 2026-02-12T00:00:00.000Z | G10: 0000059478-26-000013 | H10: us-gaap:PaymentsToAcquireOtherPropertyPlantAndEquipment | I10: c-1 | J10: 6 | K10: -6 | L10: https://www.sec.gov/Archives/edgar/data/59478/000005947826000013/lly-20251231.htm | M10: Exact tag, USD duration, exact start and end dates, no dimensions
A11: Purchases of property and equipment · current year to date | B11: 5259000000 | C11: 2026-01-01T00:00:00.000Z | D11: 2026-06-30T00:00:00.000Z | E11: 10-Q | F11: 2026-08-05T00:00:00.000Z | G11: 0000059478-26-000081 | H11: us-gaap:PaymentsToAcquireOtherPropertyPlantAndEquipment | I11: c-1 | J11: 6 | K11: -6 | L11: https://www.sec.gov/Archives/edgar/data/59478/000005947826000081/lly-20260630.htm | M11: Exact tag, USD duration, exact start and end dates, no dimensions
A12: Purchases of property and equipment · prior year to date | B12: 3207000000 | C12: 2025-01-01T00:00:00.000Z | D12: 2025-06-30T00:00:00.000Z | E12: 10-Q | F12: 2026-08-05T00:00:00.000Z | G12: 0000059478-26-000081 | H12: us-gaap:PaymentsToAcquireOtherPropertyPlantAndEquipment | I12: c-14 | J12: 6 | K12: -6 | L12: https://www.sec.gov/Archives/edgar/data/59478/000005947826000081/lly-20260630.htm | M12: Exact tag, USD duration, exact start and end dates, no dimensions
A15: Disclosure | B15: Amount as disclosed | C15: As of | D15: Form | E15: Filed | F15: Accession | G15: Source | H15: Filing location | I15: Conditions
A16: Pending AtaiBeckley acquisition | B16: Approximately $2.8B | C16: 2026-08-05T00:00:00.000Z | D16: 10-Q | E16: 2026-08-05T00:00:00.000Z | F16: 0000059478-26-000081 | G16: https://www.sec.gov/Archives/edgar/data/59478/000005947826000081/lly-20260630.htm | H16: 10-Q MD&A, p. 31 | I16: Potential payment at closing, subject to closing conditions. Not recognized as borrowing.
A17: Venture fund commitments | B17: Approximately $806M | C17: 2026-06-30T00:00:00.000Z | D17: 10-Q | E17: 2026-08-05T00:00:00.000Z | F17: 0000059478-26-000081 | G17: https://www.sec.gov/Archives/edgar/data/59478/000005947826000081/lly-20260630.htm | H17: 10-Q MD&A, p. 31; Note 8 | I17: Expected to be paid over up to ten years. Not recognized as borrowing.
A20: Review input key | B20: USD millions | C20: Label | D20: Period start | E20: Date / disclosure basis | F20: Form | G20: Filed | H20: Accession | I20: Tag | J20: Context | K20: Scale | L20: Decimals | M20: Source | N20: Filing location | O20: Source kind | P20: Dimensions | Q20: Limitations | R20: Reviewed source SHA256 | S20: Fixed coupon, fraction | T20: Compounded SOFR margin, fraction
A21: ocf | B21: 16023000000 | C21: Operating cash flow | D21: 2026-01-01T00:00:00.000Z | E21: 2026-06-30T00:00:00.000Z | F21: 10-Q | G21: 2026-08-05T00:00:00.000Z | H21: 0000059478-26-000081 | I21: us-gaap:NetCashProvidedByUsedInOperatingActivities | J21: c-1 | K21: 6 | L21: -6 | M21: https://www.sec.gov/Archives/edgar/data/59478/000005947826000081/lly-20260630.htm | N21: Cash flows p. 8 | O21: Inline XBRL | P21: None (consolidated total) | R21: 8e8f10cf3af98bc12a41985a98cfde9c2b9da8a812af18515d34ce3d8e1c1b3d
A22: capex | B22: 5259000000 | C22: Cash purchases of other PP&E | D22: 2026-01-01T00:00:00.000Z | E22: 2026-06-30T00:00:00.000Z | F22: 10-Q | G22: 2026-08-05T00:00:00.000Z | H22: 0000059478-26-000081 | I22: us-gaap:PaymentsToAcquireOtherPropertyPlantAndEquipment | J22: c-1 | K22: 6 | L22: -6 | M22: https://www.sec.gov/Archives/edgar/data/59478/000005947826000081/lly-20260630.htm | N22: Cash flows p. 8 | O22: Inline XBRL | P22: None (consolidated total) | R22: 8e8f10cf3af98bc12a41985a98cfde9c2b9da8a812af18515d34ce3d8e1c1b3d
A23: investments | B23: 604000000 | C23: Investment purchases | D23: 2026-01-01T00:00:00.000Z | E23: 2026-06-30T00:00:00.000Z | F23: 10-Q | G23: 2026-08-05T00:00:00.000Z | H23: 0000059478-26-000081 | I23: us-gaap:PaymentsToAcquireOtherInvestments | J23: c-1 | K23: 6 | L23: -6 | M23: https://www.sec.gov/Archives/edgar/data/59478/000005947826000081/lly-20260630.htm | N23: Cash flows p. 8 | O23: Inline XBRL | P23: None (consolidated total) | R23: 8e8f10cf3af98bc12a41985a98cfde9c2b9da8a812af18515d34ce3d8e1c1b3d
A24: iprd | B24: 3486000000 | C24: Purchased in-process R&D | D24: 2026-01-01T00:00:00.000Z | E24: 2026-06-30T00:00:00.000Z | F24: 10-Q | G24: 2026-08-05T00:00:00.000Z | H24: 0000059478-26-000081 | I24: us-gaap:PaymentsToAcquireInProcessResearchAndDevelopment | J24: c-1 | K24: 6 | L24: -6 | M24: https://www.sec.gov/Archives/edgar/data/59478/000005947826000081/lly-20260630.htm | N24: Cash flows p. 8 | O24: Inline XBRL | P24: None (consolidated total) | R24: 8e8f10cf3af98bc12a41985a98cfde9c2b9da8a812af18515d34ce3d8e1c1b3d
A25: acquisitions | B25: 9805000000 | C25: Acquisitions, net of cash acquired | D25: 2026-01-01T00:00:00.000Z | E25: 2026-06-30T00:00:00.000Z | F25: 10-Q | G25: 2026-08-05T00:00:00.000Z | H25: 0000059478-26-000081 | I25: us-gaap:OtherPaymentsToAcquireBusinesses | J25: c-1 | K25: 6 | L25: -6 | M25: https://www.sec.gov/Archives/edgar/data/59478/000005947826000081/lly-20260630.htm | N25: Cash flows p. 8 | O25: Inline XBRL | P25: None (consolidated total) | R25: 8e8f10cf3af98bc12a41985a98cfde9c2b9da8a812af18515d34ce3d8e1c1b3d
A26: other_investing | B26: 158000000 | C26: Other investing cash used | D26: 2026-01-01T00:00:00.000Z | E26: 2026-06-30T00:00:00.000Z | F26: 10-Q | G26: 2026-08-05T00:00:00.000Z | H26: 0000059478-26-000081 | I26: us-gaap:PaymentsForProceedsFromOtherInvestingActivities | J26: c-1 | K26: 6 | L26: -6 | M26: https://www.sec.gov/Archives/edgar/data/59478/000005947826000081/lly-20260630.htm | N26: Cash flows p. 8 | O26: Inline XBRL | P26: None (consolidated total) | R26: 8e8f10cf3af98bc12a41985a98cfde9c2b9da8a812af18515d34ce3d8e1c1b3d
A27: investing_total | B27: -19312000000 | C27: Reported net investing cash flow | D27: 2026-01-01T00:00:00.000Z | E27: 2026-06-30T00:00:00.000Z | F27: 10-Q | G27: 2026-08-05T00:00:00.000Z | H27: 0000059478-26-000081 | I27: us-gaap:NetCashProvidedByUsedInInvestingActivities | J27: c-1 | K27: 6 | L27: -6 | M27: https://www.sec.gov/Archives/edgar/data/59478/000005947826000081/lly-20260630.htm | N27: Cash flows p. 8 | O27: Inline XBRL | P27: None (consolidated total) | R27: 8e8f10cf3af98bc12a41985a98cfde9c2b9da8a812af18515d34ce3d8e1c1b3d
A28: dividends | B28: 3094000000 | C28: Cash dividends | D28: 2026-01-01T00:00:00.000Z | E28: 2026-06-30T00:00:00.000Z | F28: 10-Q | G28: 2026-08-05T00:00:00.000Z | H28: 0000059478-26-000081 | I28: us-gaap:PaymentsOfDividends | J28: c-1 | K28: 6 | L28: -6 | M28: https://www.sec.gov/Archives/edgar/data/59478/000005947826000081/lly-20260630.htm | N28: Cash flows p. 8 | O28: Inline XBRL | P28: None (consolidated total) | R28: 8e8f10cf3af98bc12a41985a98cfde9c2b9da8a812af18515d34ce3d8e1c1b3d
A29: short_debt | B29: 5284000000 | C29: Short-term borrowings, net | D29: 2026-01-01T00:00:00.000Z | E29: 2026-06-30T00:00:00.000Z | F29: 10-Q | G29: 2026-08-05T00:00:00.000Z | H29: 0000059478-26-000081 | I29: us-gaap:ProceedsFromRepaymentsOfShortTermDebt | J29: c-1 | K29: 6 | L29: -6 | M29: https://www.sec.gov/Archives/edgar/data/59478/000005947826000081/lly-20260630.htm | N29: Cash flows p. 8 | O29: Inline XBRL | P29: None (consolidated total) | R29: 8e8f10cf3af98bc12a41985a98cfde9c2b9da8a812af18515d34ce3d8e1c1b3d
A30: long_proceeds | B30: 8941000000 | C30: Long-term borrowing proceeds, net | D30: 2026-01-01T00:00:00.000Z | E30: 2026-06-30T00:00:00.000Z | F30: 10-Q | G30: 2026-08-05T00:00:00.000Z | H30: 0000059478-26-000081 | I30: us-gaap:ProceedsFromIssuanceOfLongTermDebt | J30: c-1 | K30: 6 | L30: -6 | M30: https://www.sec.gov/Archives/edgar/data/59478/000005947826000081/lly-20260630.htm | N30: Cash flows p. 8 | O30: Inline XBRL | P30: None (consolidated total) | R30: 8e8f10cf3af98bc12a41985a98cfde9c2b9da8a812af18515d34ce3d8e1c1b3d
A31: long_repayments | B31: 1623000000 | C31: Long-term debt repaid | D31: 2026-01-01T00:00:00.000Z | E31: 2026-06-30T00:00:00.000Z | F31: 10-Q | G31: 2026-08-05T00:00:00.000Z | H31: 0000059478-26-000081 | I31: us-gaap:RepaymentsOfLongTermDebt | J31: c-1 | K31: 6 | L31: -6 | M31: https://www.sec.gov/Archives/edgar/data/59478/000005947826000081/lly-20260630.htm | N31: Cash flows p. 8 | O31: Inline XBRL | P31: None (consolidated total) | R31: 8e8f10cf3af98bc12a41985a98cfde9c2b9da8a812af18515d34ce3d8e1c1b3d
A32: buybacks | B32: 3957000000 | C32: Share repurchases | D32: 2026-01-01T00:00:00.000Z | E32: 2026-06-30T00:00:00.000Z | F32: 10-Q | G32: 2026-08-05T00:00:00.000Z | H32: 0000059478-26-000081 | I32: us-gaap:PaymentsForRepurchaseOfCommonStock | J32: c-1 | K32: 6 | L32: -6 | M32: https://www.sec.gov/Archives/edgar/data/59478/000005947826000081/lly-20260630.htm | N32: Cash flows p. 8 | O32: Inline XBRL | P32: None (consolidated total) | R32: 8e8f10cf3af98bc12a41985a98cfde9c2b9da8a812af18515d34ce3d8e1c1b3d
... A36: change | B36: 1682000000 | C36: Reported cash increase | D36: 2026-01-01T00:00:00.000Z | E36: 2026-06-30T00:00:00.000Z | F36: 10-Q | G36: 2026-08-05T00:00:00.000Z | H36: 0000059478-26-000081 | I36: us-gaap:CashCashEquivalentsRestrictedCashAndRestrictedCashEquivalentsPeriodIncreaseDecreaseIncludingExchangeRateEffect | J36: c-1 | K36: 6 | L36: -6 | M36: https://www.sec.gov/Archives/edgar/data/59478/000005947826000081/lly-20260630.htm | N36: Cash flows p. 8 | O36: Inline XBRL | P36: None (consolidated total) | R36: 8e8f10cf3af98bc12a41985a98cfde9c2b9da8a812af18515d34ce3d8e1c1b3d
A37: opening | B37: 7268000000 | C37: Opening cash and equivalents | E37: 2025-12-31T00:00:00.000Z | F37: 10-Q | G37: 2026-08-05T00:00:00.000Z | H37: 0000059478-26-000081 | I37: us-gaap:CashAndCashEquivalentsAtCarryingValue | J37: c-16 | K37: 6 | L37: -6 | M37: https://www.sec.gov/Archives/edgar/data/59478/000005947826000081/lly-20260630.htm | N37: Balance sheet p. 7; cash flows p. 8 | O37: Inline XBRL | P37: None (consolidated total) | R37: 8e8f10cf3af98bc12a41985a98cfde9c2b9da8a812af18515d34ce3d8e1c1b3d
A38: closing | B38: 8950000000 | C38: Closing cash and equivalents | E38: 2026-06-30T00:00:00.000Z | F38: 10-Q | G38: 2026-08-05T00:00:00.000Z | H38: 0000059478-26-000081 | I38: us-gaap:CashAndCashEquivalentsAtCarryingValue | J38: c-15 | K38: 6 | L38: -6 | M38: https://www.sec.gov/Archives/edgar/data/59478/000005947826000081/lly-20260630.htm | N38: Balance sheet p. 7; cash flows p. 8 | O38: Inline XBRL | P38: None (consolidated total) | R38: 8e8f10cf3af98bc12a41985a98cfde9c2b9da8a812af18515d34ce3d8e1c1b3d
A39: current_debt | B39: 7050000000 | C39: Current borrowing | E39: 2026-06-30T00:00:00.000Z | F39: 10-Q | G39: 2026-08-05T00:00:00.000Z | H39: 0000059478-26-000081 | I39: us-gaap:DebtCurrent | J39: c-15 | K39: 6 | L39: -6 | M39: https://www.sec.gov/Archives/edgar/data/59478/000005947826000081/lly-20260630.htm | N39: Balance sheet p. 7 | O39: Inline XBRL | P39: None (consolidated total) | R39: 8e8f10cf3af98bc12a41985a98cfde9c2b9da8a812af18515d34ce3d8e1c1b3d
A40: noncurrent_debt | B40: 47858000000 | C40: Noncurrent borrowing | E40: 2026-06-30T00:00:00.000Z | F40: 10-Q | G40: 2026-08-05T00:00:00.000Z | H40: 0000059478-26-000081 | I40: us-gaap:LongTermDebtNoncurrent | J40: c-15 | K40: 6 | L40: -6 | M40: https://www.sec.gov/Archives/edgar/data/59478/000005947826000081/lly-20260630.htm | N40: Balance sheet p. 7 | O40: Inline XBRL | P40: None (consolidated total) | R40: 8e8f10cf3af98bc12a41985a98cfde9c2b9da8a812af18515d34ce3d8e1c1b3d
A41: contingent_current | B41: 814000000 | C41: Contingent consideration fair value: current | E41: 2026-06-30T00:00:00.000Z | F41: 10-Q | G41: 2026-08-05T00:00:00.000Z | H41: 0000059478-26-000081 | I41: us-gaap:BusinessCombinationContingentConsiderationLiabilityCurrent | J41: c-301 | K41: 6 | L41: -6 | M41: https://www.sec.gov/Archives/edgar/data/59478/000005947826000081/lly-20260630.htm | N41: Note 8 p. 17 | O41: Inline XBRL | P41: us-gaap:FairValueByFairValueHierarchyLevelAxis = us-gaap:FairValueInputsLevel3Member | R41: 8e8f10cf3af98bc12a41985a98cfde9c2b9da8a812af18515d34ce3d8e1c1b3d
A42: contingent_noncurrent | B42: 1704000000 | C42: Contingent consideration fair value: noncurrent | E42: 2026-06-30T00:00:00.000Z | F42: 10-Q | G42: 2026-08-05T00:00:00.000Z | H42: 0000059478-26-000081 | I42: us-gaap:BusinessCombinationContingentConsiderationLiabilityNoncurrent | J42: c-301 | K42: 6 | L42: -6 | M42: https://www.sec.gov/Archives/edgar/data/59478/000005947826000081/lly-20260630.htm | N42: Note 8 p. 17 | O42: Inline XBRL | P42: us-gaap:FairValueByFairValueHierarchyLevelAxis = us-gaap:FairValueInputsLevel3Member | R42: 8e8f10cf3af98bc12a41985a98cfde9c2b9da8a812af18515d34ce3d8e1c1b3d
A43: notes_2026 | B43: 1632000000 | C43: Notes due 2026 | E43: 2025-12-31T00:00:00.000Z | F43: 10-K | G43: 2026-02-12T00:00:00.000Z | H43: 0000059478-26-000013 | I43: us-gaap:DebtInstrumentCarryingAmount | J43: c-297 | K43: 6 | L43: -6 | M43: https://www.sec.gov/Archives/edgar/data/59478/000005947826000013/lly-20251231.htm | N43: Note 11 p. 76 | O43: Inline XBRL | P43: us-gaap:DebtInstrumentAxis = lly:NotesDue2026Member | R43: d45f8d1e0945df0b7b30254e96ff8c5dbd1df7d15b17c8ef7399c8e0206b7d7f
A44: notes_2027 | B44: 2516000000 | C44: Notes due 2027 | E44: 2025-12-31T00:00:00.000Z | F44: 10-K | G44: 2026-02-12T00:00:00.000Z | H44: 0000059478-26-000013 | I44: us-gaap:DebtInstrumentCarryingAmount | J44: c-301 | K44: 6 | L44: -6 | M44: https://www.sec.gov/Archives/edgar/data/59478/000005947826000013/lly-20251231.htm | N44: Note 11 p. 76 | O44: Inline XBRL | P44: us-gaap:DebtInstrumentAxis = lly:NotesDue2027Member | R44: d45f8d1e0945df0b7b30254e96ff8c5dbd1df7d15b17c8ef7399c8e0206b7d7f
A45: notes_2028 | B45: 3256000000 | C45: Notes due 2028 | E45: 2025-12-31T00:00:00.000Z | F45: 10-K | G45: 2026-02-12T00:00:00.000Z | H45: 0000059478-26-000013 | I45: us-gaap:DebtInstrumentCarryingAmount | J45: c-305 | K45: 6 | L45: -6 | M45: https://www.sec.gov/Archives/edgar/data/59478/000005947826000013/lly-20251231.htm | N45: Note 11 p. 76 | O45: Inline XBRL | P45: us-gaap:DebtInstrumentAxis = lly:NotesDue2028Member | R45: d45f8d1e0945df0b7b30254e96ff8c5dbd1df7d15b17c8ef7399c8e0206b7d7f
A46: notes_2029 | B46: 3077000000 | C46: Notes due 2029 | E46: 2025-12-31T00:00:00.000Z | F46: 10-K | G46: 2026-02-12T00:00:00.000Z | H46: 0000059478-26-000013 | I46: us-gaap:DebtInstrumentCarryingAmount | J46: c-309 | K46: 6 | L46: -6 | M46: https://www.sec.gov/Archives/edgar/data/59478/000005947826000013/lly-20251231.htm | N46: Note 11 p. 76 | O46: Inline XBRL | P46: us-gaap:DebtInstrumentAxis = lly:NotesDue2029Member | R46: d45f8d1e0945df0b7b30254e96ff8c5dbd1df7d15b17c8ef7399c8e0206b7d7f
A47: notes_2030 | B47: 2132000000 | C47: Notes due 2030 | E47: 2025-12-31T00:00:00.000Z | F47: 10-K | G47: 2026-02-12T00:00:00.000Z | H47: 0000059478-26-000013 | I47: us-gaap:DebtInstrumentCarryingAmount | J47: c-313 | K47: 6 | L47: -6 | M47: https://www.sec.gov/Archives/edgar/data/59478/000005947826000013/lly-20251231.htm | N47: Note 11 p. 76 | O47: Inline XBRL | P47: us-gaap:DebtInstrumentAxis = lly:NotesDue2030Member | R47: d45f8d1e0945df0b7b30254e96ff8c5dbd1df7d15b17c8ef7399c8e0206b7d7f
A48: notes_20312040 | B48: 11582000000 | C48: Notes due 2031–2040 | E48: 2025-12-31T00:00:00.000Z | F48: 10-K | G48: 2026-02-12T00:00:00.000Z | H48: 0000059478-26-000013 | I48: us-gaap:DebtInstrumentCarryingAmount | J48: c-317 | K48: 6 | L48: -6 | M48: https://www.sec.gov/Archives/edgar/data/59478/000005947826000013/lly-20251231.htm | N48: Note 11 p. 76 | O48: Inline XBRL | P48: us-gaap:DebtInstrumentAxis = lly:NotesDue20312040Member | R48: d45f8d1e0945df0b7b30254e96ff8c5dbd1df7d15b17c8ef7399c8e0206b7d7f
... A57: facility_2029 | B57: 4000000000 | C57: Facility expires December 2029 | E57: 2025-12-31T00:00:00.000Z | F57: 10-K | G57: 2026-02-12T00:00:00.000Z | H57: 0000059478-26-000013 | I57: us-gaap:LineOfCreditFacilityMaximumBorrowingCapacity | J57: c-333 | K57: 9 | L57: INF | M57: https://www.sec.gov/Archives/edgar/data/59478/000005947826000013/lly-20251231.htm | N57: Note 11 p. 76; MD&A p. 51 | O57: Inline XBRL | P57: us-gaap:DebtInstrumentRedemptionPeriodAxis = lly:MaturityDateDecember2029Member | R57: d45f8d1e0945df0b7b30254e96ff8c5dbd1df7d15b17c8ef7399c8e0206b7d7f
A58: unused_june | B58: 10100000000 | C58: Unused committed facilities | E58: 2026-06-30T00:00:00.000Z | F58: 10-Q | G58: 2026-08-05T00:00:00.000Z | H58: 0000059478-26-000081 | M58: https://www.sec.gov/Archives/edgar/data/59478/000005947826000081/lly-20260630.htm | N58: MD&A p. 31 | O58: Reviewed filing text | P58: None (consolidated total) | Q58: Of this, $10B supports commercial paper. Not cash or verified drawable credit; do not add CP capacity again. Agreement conditions and facility-by-facility June composition are Unavailable. | R58: 8e8f10cf3af98bc12a41985a98cfde9c2b9da8a812af18515d34ce3d8e1c1b3d
A59: cp_support | B59: 10000000000 | C59: Facilities supporting commercial paper | E59: 2026-06-30T00:00:00.000Z | F59: 10-Q | G59: 2026-08-05T00:00:00.000Z | H59: 0000059478-26-000081 | M59: https://www.sec.gov/Archives/edgar/data/59478/000005947826000081/lly-20260630.htm | N59: MD&A p. 31 | O59: Reviewed filing text | P59: None (consolidated total) | Q59: Included in the $10.1B; not another source of funds. | R59: 8e8f10cf3af98bc12a41985a98cfde9c2b9da8a812af18515d34ce3d8e1c1b3d
A60: atai | B60: 2800000000 | C60: Pending AtaiBeckley acquisition | E60: Disclosed August 5, 2026 | F60: 10-Q | G60: 2026-08-05T00:00:00.000Z | H60: 0000059478-26-000081 | M60: https://www.sec.gov/Archives/edgar/data/59478/000005947826000081/lly-20260630.htm | N60: MD&A p. 31 | O60: Reviewed filing text | P60: None (consolidated total) | Q60: Payable at closing, subject to conditions. Disclosed after quarter end; closing date, completion and funding allocation are not established here. | R60: 8e8f10cf3af98bc12a41985a98cfde9c2b9da8a812af18515d34ce3d8e1c1b3d
A61: unpaid_kelonia | B61: 208000000 | C61: Unpaid Kelonia cash consideration | E61: 2026-06-30T00:00:00.000Z | F61: 10-Q | G61: 2026-08-05T00:00:00.000Z | H61: 0000059478-26-000081 | M61: https://www.sec.gov/Archives/edgar/data/59478/000005947826000081/lly-20260630.htm | N61: Note 4 p. 13 | O61: Reviewed filing text | P61: None (consolidated total) | Q61: Payment date Unavailable. Separate from cash already paid and from contingent-consideration fair value. | R61: 8e8f10cf3af98bc12a41985a98cfde9c2b9da8a812af18515d34ce3d8e1c1b3d
A62: unpaid_centessa | B62: 88000000 | C62: Unpaid Centessa cash consideration | E62: 2026-06-30T00:00:00.000Z | F62: 10-Q | G62: 2026-08-05T00:00:00.000Z | H62: 0000059478-26-000081 | M62: https://www.sec.gov/Archives/edgar/data/59478/000005947826000081/lly-20260630.htm | N62: Note 4 p. 13 | O62: Reviewed filing text | P62: None (consolidated total) | Q62: Payment date Unavailable. Do not add to paid acquisition cash or contingent-consideration fair value. | R62: 8e8f10cf3af98bc12a41985a98cfde9c2b9da8a812af18515d34ce3d8e1c1b3d
A63: july_paid | B63: 2000000000 | C63: July infectious-disease acquisitions: cash paid | E63: July 2026 | F63: 10-Q | G63: 2026-08-05T00:00:00.000Z | H63: 0000059478-26-000081 | M63: https://www.sec.gov/Archives/edgar/data/59478/000005947826000081/lly-20260630.htm | N63: MD&A p. 31; Note 4 pp. 13–14 | O63: Reviewed filing text | P63: None (consolidated total) | Q63: Already paid after June. Other July cash flows are unknown; June cash less this payment is not a current cash balance. | R63: 8e8f10cf3af98bc12a41985a98cfde9c2b9da8a812af18515d34ce3d8e1c1b3d
A64: july_ceiling | B64: 3900000000 | C64: July acquisitions: aggregate consideration up to | E64: July 2026 | F64: 10-Q | G64: 2026-08-05T00:00:00.000Z | H64: 0000059478-26-000081 | M64: https://www.sec.gov/Archives/edgar/data/59478/000005947826000081/lly-20260630.htm | N64: Note 4 pp. 13–14 | O64: Reviewed filing text | P64: None (consolidated total) | Q64: Includes upfront cash and potential clinical, regulatory and commercial milestones. Includes the approximately $2B paid; do not add the two amounts or infer a precise remaining cash bill. | R64: 8e8f10cf3af98bc12a41985a98cfde9c2b9da8a812af18515d34ce3d8e1c1b3d
A65: vc | B65: 806000000 | C65: Unfunded venture fund commitments | E65: 2026-06-30T00:00:00.000Z | F65: 10-Q | G65: 2026-08-05T00:00:00.000Z | H65: 0000059478-26-000081 | M65: https://www.sec.gov/Archives/edgar/data/59478/000005947826000081/lly-20260630.htm | N65: MD&A p. 31 | O65: Reviewed filing text | P65: None (consolidated total) | Q65: Expected to be paid over up to ten years. Individual capital-call dates are Unavailable. | R65: 8e8f10cf3af98bc12a41985a98cfde9c2b9da8a812af18515d34ce3d8e1c1b3d
A66: manufacturing | B66: 10000000000 | C66: Development-medicine supply arrangements: up to | E66: 2025-12-31T00:00:00.000Z | F66: 10-K | G66: 2026-02-12T00:00:00.000Z | H66: 0000059478-26-000013 | M66: https://www.sec.gov/Archives/edgar/data/59478/000005947826000013/lly-20251231.htm | N66: MD&A p. 51 | O66: Reviewed filing text | P66: None (consolidated total) | Q66: Payments if specified purchases are not met under executed manufacturing and supply agreements; durations generally up to eight years. Not an unconditional $10B bill. Updated June ceiling, annual payments and overlap with other spending are Unavailable. | R66: d45f8d1e0945df0b7b30254e96ff8c5dbd1df7d15b17c8ef7399c8e0206b7d7f
A67: indiana | B67: 4500000000 | C67: Additional Indiana manufacturing investment | E67: Announced August 5, 2026 | F67: 8-K Ex. 99.1 | G67: 2026-08-05T00:00:00.000Z | H67: 0000059478-26-000077 | M67: https://www.sec.gov/Archives/edgar/data/59478/000005947826000077/q226lillysalesandearningsp.htm | N67: Highlights; Other announcements | O67: Reviewed filing text | P67: None (consolidated total) | Q67: Release says committed an additional $4.5B. Contractual payment schedule, spending to date and overlap with capex or supply commitments are not established by this release. Not added to debt or the $10B ceiling. | R67: 5397056cb6aebc1496e22de6f9c8b062b11ff0c7f5ee30428e3f68fc8aea748a
A68: coverage_fy_revenue | B68: 65179000000 | C68: fy revenue | D68: 2025-01-01T00:00:00.000Z | E68: 2025-12-31T00:00:00.000Z | F68: 10-K | G68: 2026-02-12T00:00:00.000Z | H68: 0000059478-26-000013 | I68: us-gaap:Revenues | J68: c-1 | K68: 6 | L68: -6 | M68: https://www.sec.gov/Archives/edgar/data/59478/000005947826000013/lly-20251231.htm | N68: Consolidated operations p. 57 | O68: Inline XBRL | P68: None (consolidated total) | Q68: Exact tag, duration, USD and Lilly CIK; no dimensions; consolidated operations table only | R68: d45f8d1e0945df0b7b30254e96ff8c5dbd1df7d15b17c8ef7399c8e0206b7d7f
A69: coverage_fy_cost_sales | B69: 11052000000 | C69: fy cost_sales | D69: 2025-01-01T00:00:00.000Z | E69: 2025-12-31T00:00:00.000Z | F69: 10-K | G69: 2026-02-12T00:00:00.000Z | H69: 0000059478-26-000013 | I69: us-gaap:CostOfGoodsAndServicesSold | J69: c-1 | K69: 6 | L69: -6 | M69: https://www.sec.gov/Archives/edgar/data/59478/000005947826000013/lly-20251231.htm | N69: Consolidated operations p. 57 | O69: Inline XBRL | P69: None (consolidated total) | Q69: Exact tag, duration, USD and Lilly CIK; no dimensions; consolidated operations table only | R69: d45f8d1e0945df0b7b30254e96ff8c5dbd1df7d15b17c8ef7399c8e0206b7d7f
A70: coverage_fy_rd | B70: 13337000000 | C70: fy rd | D70: 2025-01-01T00:00:00.000Z | E70: 2025-12-31T00:00:00.000Z | F70: 10-K | G70: 2026-02-12T00:00:00.000Z | H70: 0000059478-26-000013 | I70: us-gaap:ResearchAndDevelopmentExpenseExcludingAcquiredInProcessCost | J70: c-1 | K70: 6 | L70: -6 | M70: https://www.sec.gov/Archives/edgar/data/59478/000005947826000013/lly-20251231.htm | N70: Consolidated operations p. 57 | O70: Inline XBRL | P70: None (consolidated total) | Q70: Exact tag, duration, USD and Lilly CIK; no dimensions; consolidated operations table only | R70: d45f8d1e0945df0b7b30254e96ff8c5dbd1df7d15b17c8ef7399c8e0206b7d7f
A71: coverage_fy_sga | B71: 11094000000 | C71: fy sga | D71: 2025-01-01T00:00:00.000Z | E71: 2025-12-31T00:00:00.000Z | F71: 10-K | G71: 2026-02-12T00:00:00.000Z | H71: 0000059478-26-000013 | I71: us-gaap:SellingGeneralAndAdministrativeExpense | J71: c-1 | K71: 6 | L71: -6 | M71: https://www.sec.gov/Archives/edgar/data/59478/000005947826000013/lly-20251231.htm | N71: Consolidated operations p. 57 | O71: Inline XBRL | P71: None (consolidated total) | Q71: Exact tag, duration, USD and Lilly CIK; no dimensions; consolidated operations table only | R71: d45f8d1e0945df0b7b30254e96ff8c5dbd1df7d15b17c8ef7399c8e0206b7d7f
A72: coverage_fy_iprd | B72: 2910000000 | C72: fy iprd | D72: 2025-01-01T00:00:00.000Z | E72: 2025-12-31T00:00:00.000Z | F72: 10-K | G72: 2026-02-12T00:00:00.000Z | H72: 0000059478-26-000013 | I72: us-gaap:ResearchAndDevelopmentAssetAcquiredOtherThanThroughBusinessCombinationWrittenOff | J72: c-1 | K72: 6 | L72: -6 | M72: https://www.sec.gov/Archives/edgar/data/59478/000005947826000013/lly-20251231.htm | N72: Consolidated operations p. 57 | O72: Inline XBRL | P72: None (consolidated total) | Q72: Exact tag, duration, USD and Lilly CIK; no dimensions; consolidated operations table only | R72: d45f8d1e0945df0b7b30254e96ff8c5dbd1df7d15b17c8ef7399c8e0206b7d7f
A73: coverage_fy_special | B73: 484000000 | C73: fy special | D73: 2025-01-01T00:00:00.000Z | E73: 2025-12-31T00:00:00.000Z | F73: 10-K | G73: 2026-02-12T00:00:00.000Z | H73: 0000059478-26-000013 | I73: us-gaap:RestructuringSettlementAndImpairmentProvisions | J73: c-1 | K73: 6 | L73: -6 | M73: https://www.sec.gov/Archives/edgar/data/59478/000005947826000013/lly-20251231.htm | N73: Consolidated operations p. 57 | O73: Inline XBRL | P73: None (consolidated total) | Q73: Exact tag, duration, USD and Lilly CIK; no dimensions; consolidated operations table only | R73: d45f8d1e0945df0b7b30254e96ff8c5dbd1df7d15b17c8ef7399c8e0206b7d7f
A74: coverage_fy_other_income | B74: -571000000 | C74: fy other_income | D74: 2025-01-01T00:00:00.000Z | E74: 2025-12-31T00:00:00.000Z | F74: 10-K | G74: 2026-02-12T00:00:00.000Z | H74: 0000059478-26-000013 | I74: us-gaap:NonoperatingIncomeExpense | J74: c-1 | K74: 6 | L74: -6 | M74: https://www.sec.gov/Archives/edgar/data/59478/000005947826000013/lly-20251231.htm | N74: Consolidated operations p. 57 | O74: Inline XBRL | P74: None (consolidated total) | Q74: Exact tag, duration, USD and Lilly CIK; no dimensions; consolidated operations table only | R74: d45f8d1e0945df0b7b30254e96ff8c5dbd1df7d15b17c8ef7399c8e0206b7d7f
A75: coverage_fy_pretax | B75: 25731000000 | C75: fy pretax | D75: 2025-01-01T00:00:00.000Z | E75: 2025-12-31T00:00:00.000Z | F75: 10-K | G75: 2026-02-12T00:00:00.000Z | H75: 0000059478-26-000013 | I75: us-gaap:IncomeLossFromContinuingOperationsBeforeIncomeTaxesExtraordinaryItemsNoncontrollingInterest | J75: c-1 | K75: 6 | L75: -6 | M75: https://www.sec.gov/Archives/edgar/data/59478/000005947826000013/lly-20251231.htm | N75: Consolidated operations p. 57 | O75: Inline XBRL | P75: None (consolidated total) | Q75: Exact tag, duration, USD and Lilly CIK; no dimensions; consolidated operations table only | R75: d45f8d1e0945df0b7b30254e96ff8c5dbd1df7d15b17c8ef7399c8e0206b7d7f
A76: coverage_fy_interest | B76: 895000000 | C76: fy interest | D76: 2025-01-01T00:00:00.000Z | E76: 2025-12-31T00:00:00.000Z | F76: 10-K | G76: 2026-02-12T00:00:00.000Z | H76: 0000059478-26-000013 | I76: us-gaap:InterestExpenseNonoperating | J76: c-1 | K76: 6 | L76: -6 | M76: https://www.sec.gov/Archives/edgar/data/59478/000005947826000013/lly-20251231.htm | N76: Note 11 p. 77 | O76: Inline XBRL | P76: None (consolidated total) | Q76: Exact tag, duration, USD and Lilly CIK; no dimensions | R76: d45f8d1e0945df0b7b30254e96ff8c5dbd1df7d15b17c8ef7399c8e0206b7d7f
A77: coverage_current_revenue | B77: 42773000000 | C77: current revenue | D77: 2026-01-01T00:00:00.000Z | E77: 2026-06-30T00:00:00.000Z | F77: 10-Q | G77: 2026-08-05T00:00:00.000Z | H77: 0000059478-26-000081 | I77: us-gaap:Revenues | J77: c-1 | K77: 6 | L77: -6 | M77: https://www.sec.gov/Archives/edgar/data/59478/000005947826000081/lly-20260630.htm | N77: Consolidated operations p. 5 | O77: Inline XBRL | P77: None (consolidated total) | Q77: Exact tag, duration, USD and Lilly CIK; no dimensions; consolidated operations table only | R77: 8e8f10cf3af98bc12a41985a98cfde9c2b9da8a812af18515d34ce3d8e1c1b3d
A78: coverage_current_cost_sales | B78: 6845000000 | C78: current cost_sales | D78: 2026-01-01T00:00:00.000Z | E78: 2026-06-30T00:00:00.000Z | F78: 10-Q | G78: 2026-08-05T00:00:00.000Z | H78: 0000059478-26-000081 | I78: us-gaap:CostOfGoodsAndServicesSold | J78: c-1 | K78: 6 | L78: -6 | M78: https://www.sec.gov/Archives/edgar/data/59478/000005947826000081/lly-20260630.htm | N78: Consolidated operations p. 5 | O78: Inline XBRL | P78: None (consolidated total) | Q78: Exact tag, duration, USD and Lilly CIK; no dimensions; consolidated operations table only | R78: 8e8f10cf3af98bc12a41985a98cfde9c2b9da8a812af18515d34ce3d8e1c1b3d
A79: coverage_current_rd | B79: 7329000000 | C79: current rd | D79: 2026-01-01T00:00:00.000Z | E79: 2026-06-30T00:00:00.000Z | F79: 10-Q | G79: 2026-08-05T00:00:00.000Z | H79: 0000059478-26-000081 | I79: us-gaap:ResearchAndDevelopmentExpenseExcludingAcquiredInProcessCost | J79: c-1 | K79: 6 | L79: -6 | M79: https://www.sec.gov/Archives/edgar/data/59478/000005947826000081/lly-20260630.htm | N79: Consolidated operations p. 5 | O79: Inline XBRL | P79: None (consolidated total) | Q79: Exact tag, duration, USD and Lilly CIK; no dimensions; consolidated operations table only | R79: 8e8f10cf3af98bc12a41985a98cfde9c2b9da8a812af18515d34ce3d8e1c1b3d
... A94: coverage_prior_interest | B94: 493000000 | C94: prior interest | D94: 2025-01-01T00:00:00.000Z | E94: 2025-06-30T00:00:00.000Z | F94: 10-Q | G94: 2026-08-05T00:00:00.000Z | H94: 0000059478-26-000081 | I94: us-gaap:InterestExpenseNonoperating | J94: c-398 | K94: 6 | L94: -6 | M94: https://www.sec.gov/Archives/edgar/data/59478/000005947826000081/lly-20260630.htm | N94: Note 11 p. 23 | O94: Inline XBRL | P94: us-gaap:StatementBusinessSegmentsAxis = lly:ReportableSegmentMember | Q94: Exact tag, duration, USD and Lilly CIK; exact single-segment dimension | R94: 8e8f10cf3af98bc12a41985a98cfde9c2b9da8a812af18515d34ce3d8e1c1b3d
A95: may_notes_0 | B95: 750000000 | C95: Floating 2028 — May 20 initial issue | E95: 2028-05-20T00:00:00.000Z | F95: 8-K Ex. 4.4 | G95: 2026-05-20T00:00:00.000Z | H95: 0001193125-26-232707 | M95: https://www.sec.gov/Archives/edgar/data/59478/000119312526232707/d148580dex44.htm | N95: Certificate clauses (iii)–(v); note forms | O95: Reviewed contract text | P95: None (consolidated total) | Q95: Initial issue principal, not June outstanding balance. Issued 2026-05-20. Stated maturity subject to applicable business-day, redemption and default provisions. Not added to June debt or the December carrying-amount table. | R95: abe96195bc60dfbb1bbdb90af64d2e548b2b743cfe34901cdf512542c9c576b9 | T95: 0.0035
A96: may_notes_1 | B96: 500000000 | C96: Floating 2029 — May 20 initial issue | E96: 2029-05-20T00:00:00.000Z | F96: 8-K Ex. 4.4 | G96: 2026-05-20T00:00:00.000Z | H96: 0001193125-26-232707 | M96: https://www.sec.gov/Archives/edgar/data/59478/000119312526232707/d148580dex44.htm | N96: Certificate clauses (iii)–(v); note forms | O96: Reviewed contract text | P96: None (consolidated total) | Q96: Initial issue principal, not June outstanding balance. Issued 2026-05-20. Stated maturity subject to applicable business-day, redemption and default provisions. Not added to June debt or the December carrying-amount table. | R96: abe96195bc60dfbb1bbdb90af64d2e548b2b743cfe34901cdf512542c9c576b9 | T96: 0.0046
A97: may_notes_2 | B97: 750000000 | C97: Fixed 2029 — May 20 initial issue | E97: 2029-05-20T00:00:00.000Z | F97: 8-K Ex. 4.3 | G97: 2026-05-20T00:00:00.000Z | H97: 0001193125-26-232707 | M97: https://www.sec.gov/Archives/edgar/data/59478/000119312526232707/d148580dex43.htm | N97: Certificate clauses (iii)–(v); note forms | O97: Reviewed contract text | P97: None (consolidated total) | Q97: Initial issue principal, not June outstanding balance. Issued 2026-05-20. Stated maturity subject to applicable business-day, redemption and default provisions. Not added to June debt or the December carrying-amount table. | R97: 23483435eff9194a1858f9a71159cb4d3d661db65eff0ff4d950bb7f4e783b97 | S97: 0.0415
A98: may_notes_3 | B98: 1500000000 | C98: Fixed 2031 — May 20 initial issue | E98: 2031-05-20T00:00:00.000Z | F98: 8-K Ex. 4.3 | G98: 2026-05-20T00:00:00.000Z | H98: 0001193125-26-232707 | M98: https://www.sec.gov/Archives/edgar/data/59478/000119312526232707/d148580dex43.htm | N98: Certificate clauses (iii)–(v); note forms | O98: Reviewed contract text | P98: None (consolidated total) | Q98: Initial issue principal, not June outstanding balance. Issued 2026-05-20. Stated maturity subject to applicable business-day, redemption and default provisions. Not added to June debt or the December carrying-amount table. | R98: 23483435eff9194a1858f9a71159cb4d3d661db65eff0ff4d950bb7f4e783b97 | S98: 0.04375
A99: may_notes_4 | B99: 1250000000 | C99: Fixed 2033 — May 20 initial issue | E99: 2033-05-20T00:00:00.000Z | F99: 8-K Ex. 4.3 | G99: 2026-05-20T00:00:00.000Z | H99: 0001193125-26-232707 | M99: https://www.sec.gov/Archives/edgar/data/59478/000119312526232707/d148580dex43.htm | N99: Certificate clauses (iii)–(v); note forms | O99: Reviewed contract text | P99: None (consolidated total) | Q99: Initial issue principal, not June outstanding balance. Issued 2026-05-20. Stated maturity subject to applicable business-day, redemption and default provisions. Not added to June debt or the December carrying-amount table. | R99: 23483435eff9194a1858f9a71159cb4d3d661db65eff0ff4d950bb7f4e783b97 | S99: 0.0465
A100: may_notes_5 | B100: 1500000000 | C100: Fixed 2036 — May 20 initial issue | E100: 2036-05-20T00:00:00.000Z | F100: 8-K Ex. 4.3 | G100: 2026-05-20T00:00:00.000Z | H100: 0001193125-26-232707 | M100: https://www.sec.gov/Archives/edgar/data/59478/000119312526232707/d148580dex43.htm | N100: Certificate clauses (iii)–(v); note forms | O100: Reviewed contract text | P100: None (consolidated total) | Q100: Initial issue principal, not June outstanding balance. Issued 2026-05-20. Stated maturity subject to applicable business-day, redemption and default provisions. Not added to June debt or the December carrying-amount table. | R100: 23483435eff9194a1858f9a71159cb4d3d661db65eff0ff4d950bb7f4e783b97 | S100: 0.0485
A101: may_notes_6 | B101: 1750000000 | C101: Fixed 2056 — May 20 initial issue | E101: 2056-05-20T00:00:00.000Z | F101: 8-K Ex. 4.3 | G101: 2026-05-20T00:00:00.000Z | H101: 0001193125-26-232707 | M101: https://www.sec.gov/Archives/edgar/data/59478/000119312526232707/d148580dex43.htm | N101: Certificate clauses (iii)–(v); note forms | O101: Reviewed contract text | P101: None (consolidated total) | Q101: Initial issue principal, not June outstanding balance. Issued 2026-05-20. Stated maturity subject to applicable business-day, redemption and default provisions. Not added to June debt or the December carrying-amount table. | R101: 23483435eff9194a1858f9a71159cb4d3d661db65eff0ff4d950bb7f4e783b97 | S101: 0.056
A102: may_notes_7 | B102: 1000000000 | C102: Fixed 2066 — May 20 initial issue | E102: 2066-05-20T00:00:00.000Z | F102: 8-K Ex. 4.3 | G102: 2026-05-20T00:00:00.000Z | H102: 0001193125-26-232707 | M102: https://www.sec.gov/Archives/edgar/data/59478/000119312526232707/d148580dex43.htm | N102: Certificate clauses (iii)–(v); note forms | O102: Reviewed contract text | P102: None (consolidated total) | Q102: Initial issue principal, not June outstanding balance. Issued 2026-05-20. Stated maturity subject to applicable business-day, redemption and default provisions. Not added to June debt or the December carrying-amount table. | R102: 23483435eff9194a1858f9a71159cb4d3d661db65eff0ff4d950bb7f4e783b97 | S102: 0.057
A103: may_issue_control | B103: 9000000000 | C103: Reported completed May issue, initial principal | E103: 2026-05-20T00:00:00.000Z | F103: 8-K | G103: 2026-05-20T00:00:00.000Z | H103: 0001193125-26-232707 | M103: https://www.sec.gov/Archives/edgar/data/59478/000119312526232707/d148580d8k.htm | N103: Item 8.01, completed offering | O103: Reviewed filing text | P103: None (consolidated total) | Q103: Initial issue principal, not net cash proceeds, current outstanding debt or unused financing. | R103: e88aeee8cddfc4b3459ec97cd166010b955ae2d8e5bcc2e59913f995c2e233f9
A106: Funding conclusion evidence | B106: Filing / filed date | C106: Accession | D106: Location | L106: SEC source
A107: Near-term obligations | B107: 10-Q filed Aug 5, 2026 | C107: 0000059478-26-000081 | D107: pp. 7–8, 12–14, 17, 23, 31 | L107: https://www.sec.gov/Archives/edgar/data/59478/000005947826000081/lly-20260630.htm
A108: Resources and access | B108: 10-Q filed Aug 5, 2026 | C108: 0000059478-26-000081 | D108: pp. 7–8, 12–14, 17, 23, 31 | L108: https://www.sec.gov/Archives/edgar/data/59478/000005947826000081/lly-20260630.htm
A109: Resources and access | B109: 10-K filed Feb 12, 2026 | C109: 0000059478-26-000013 | D109: pp. 51, 57, 76–77 | L109: https://www.sec.gov/Archives/edgar/data/59478/000005947826000013/lly-20251231.htm
A110: Competing cash uses | B110: 10-Q filed Aug 5, 2026 | C110: 0000059478-26-000081 | D110: pp. 7–8, 12–14, 17, 23, 31 | L110: https://www.sec.gov/Archives/edgar/data/59478/000005947826000081/lly-20260630.htm
A111: Competing cash uses | B111: Earnings exhibit filed Aug 5, 2026 | C111: 0000059478-26-000077 | D111: Other announcements | L111: https://www.sec.gov/Archives/edgar/data/59478/000005947826000077/q226lillysalesandearningsp.htm
A112: Decisive unknowns | B112: 10-Q filed Aug 5, 2026 | C112: 0000059478-26-000081 | D112: pp. 7–8, 12–14, 17, 23, 31 | L112: https://www.sec.gov/Archives/edgar/data/59478/000005947826000081/lly-20260630.htm
A113: Decisive unknowns | B113: 10-K filed Feb 12, 2026 | C113: 0000059478-26-000013 | D113: pp. 51, 57, 76–77 | L113: https://www.sec.gov/Archives/edgar/data/59478/000005947826000013/lly-20251231.htm
A114: Decisive unknowns | B114: Earnings exhibit filed Aug 5, 2026 | C114: 0000059478-26-000077 | D114: Other announcements | L114: https://www.sec.gov/Archives/edgar/data/59478/000005947826000077/q226lillysalesandearningsp.htm
A115: Historical coverage | B115: 10-Q filed Aug 5, 2026 | C115: 0000059478-26-000081 | D115: Operations p. 5; segment Note 11 p. 23 | L115: https://www.sec.gov/Archives/edgar/data/59478/000005947826000081/lly-20260630.htm
A116: Historical coverage | B116: 10-K filed Feb 12, 2026 | C116: 0000059478-26-000013 | D116: Operations p. 57; Borrowings Note 11 p. 77 | L116: https://www.sec.gov/Archives/edgar/data/59478/000005947826000013/lly-20251231.htm
A119: Input | B119: USD millions | C119: Period start | D119: Period end | E119: Form | F119: Filed | G119: Accession | H119: Tag | I119: Context | J119: Scale | K119: Decimals | L119: Source | M119: Filing location | N119: Selection / Unavailable reason | O119: Reviewed source SHA256
A120: Current borrowing | B120: 7050000000 | D120: 2026-06-30T00:00:00.000Z | E120: 10-Q | F120: 2026-08-05T00:00:00.000Z | G120: 0000059478-26-000081 | H120: us-gaap:DebtCurrent | L120: https://www.sec.gov/Archives/edgar/data/59478/000005947826000081/lly-20260630.htm | M120: 10-Q balance sheet, p. 7 | N120: USD instant at the balance-sheet date, from the latest original 10-K or 10-Q itself
A121: Noncurrent borrowing | B121: 47858000000 | D121: 2026-06-30T00:00:00.000Z | E121: 10-Q | F121: 2026-08-05T00:00:00.000Z | G121: 0000059478-26-000081 | H121: us-gaap:LongTermDebtNoncurrent | L121: https://www.sec.gov/Archives/edgar/data/59478/000005947826000081/lly-20260630.htm | M121: 10-Q balance sheet, p. 7 | N121: USD instant at the balance-sheet date, from the latest original 10-K or 10-Q itself
A122: Latest-date lease liabilities — Unavailable | D122: 2026-06-30T00:00:00.000Z | E122: 10-Q | F122: 2026-08-05T00:00:00.000Z | G122: 0000059478-26-000081 | L122: https://www.sec.gov/Archives/edgar/data/59478/000005947826000081/lly-20260630.htm | M122: 10-Q balance sheet, p. 7 | N122: USD instant at the balance-sheet date, from the latest original 10-K or 10-Q itself Latest-date lease liabilities Unavailable; no checked amount in the 10-Q.
A123: Operating lease liabilities — current | B123: 222000000 | D123: 2025-12-31T00:00:00.000Z | E123: 10-K | F123: 2026-02-12T00:00:00.000Z | G123: 0000059478-26-000013 | H123: us-gaap:OperatingLeaseLiabilityCurrent | I123: c-16 | J123: 6 | K123: -6 | L123: https://www.sec.gov/Archives/edgar/data/59478/000005947826000013/lly-20251231.htm | M123: 10-K Note 10, p. 76 | N123: Exact prefixed tag; exact stated instant; USD; no dimensions; agreeing duplicates. | O123: d45f8d1e0945df0b7b30254e96ff8c5dbd1df7d15b17c8ef7399c8e0206b7d7f
A124: Operating lease liabilities — noncurrent | B124: 1140000000 | D124: 2025-12-31T00:00:00.000Z | E124: 10-K | F124: 2026-02-12T00:00:00.000Z | G124: 0000059478-26-000013 | H124: us-gaap:OperatingLeaseLiabilityNoncurrent | I124: c-16 | J124: 6 | K124: -6 | L124: https://www.sec.gov/Archives/edgar/data/59478/000005947826000013/lly-20251231.htm | M124: 10-K Note 10, p. 76 | N124: Exact prefixed tag; exact stated instant; USD; no dimensions; agreeing duplicates. | O124: d45f8d1e0945df0b7b30254e96ff8c5dbd1df7d15b17c8ef7399c8e0206b7d7f
A125: Finance lease liabilities — requested date, Unavailable | D125: 2026-06-30T00:00:00.000Z | E125: 10-Q | F125: 2026-08-05T00:00:00.000Z | G125: 0000059478-26-000081 | L125: https://www.sec.gov/Archives/edgar/data/59478/000005947826000081/lly-20260630.htm | M125: 10-Q review; June amount not established | N125: No checked June amount. The 10-K describes operating leases only; finance leases are not reported, which is not zero.
A126: Leases not yet commenced — Unavailable | D126: 2026-06-30T00:00:00.000Z | E126: 10-Q | F126: 2026-08-05T00:00:00.000Z | G126: 0000059478-26-000081 | L126: https://www.sec.gov/Archives/edgar/data/59478/000005947826000081/lly-20260630.htm | M126: Saved pilot evidence; 10-Q review | N126: No checked amount for leases not yet commenced is established in the saved pilot evidence. Unavailable does not mean zero.
A129: Input | B129: USD millions | C129: Period start | D129: Period end | E129: Form | F129: Filed | G129: Accession | H129: Tag | I129: Context | J129: Scale | K129: Decimals | L129: Source | M129: Selection rule | N129: Unavailable reason | O129: Notes
A130: Cash and cash equivalents | B130: 7268000000 | D130: 2025-12-31T00:00:00.000Z | E130: 10-K | F130: 2026-02-12T00:00:00.000Z | G130: 0000059478-26-000013 | H130: us-gaap:CashAndCashEquivalentsAtCarryingValue | I130: c-16 | J130: 6 | K130: -6 | L130: https://www.sec.gov/Archives/edgar/data/59478/000005947826000013/lly-20251231.htm | M130: 10-K balance sheet p. 59; cash flows p. 61 | O130: d45f8d1e0945df0b7b30254e96ff8c5dbd1df7d15b17c8ef7399c8e0206b7d7f
A131: Current assets | B131: 55629000000 | D131: 2025-12-31T00:00:00.000Z | E131: 10-K | F131: 2026-02-12T00:00:00.000Z | G131: 0000059478-26-000013 | H131: us-gaap:AssetsCurrent | I131: c-16 | J131: 6 | K131: -6 | L131: https://www.sec.gov/Archives/edgar/data/59478/000005947826000013/lly-20251231.htm | M131: 10-K balance sheet p. 59; cash flows p. 61 | O131: d45f8d1e0945df0b7b30254e96ff8c5dbd1df7d15b17c8ef7399c8e0206b7d7f
A132: Current liabilities | B132: 35228000000 | D132: 2025-12-31T00:00:00.000Z | E132: 10-K | F132: 2026-02-12T00:00:00.000Z | G132: 0000059478-26-000013 | H132: us-gaap:LiabilitiesCurrent | I132: c-16 | J132: 6 | K132: -6 | L132: https://www.sec.gov/Archives/edgar/data/59478/000005947826000013/lly-20251231.htm | M132: 10-K balance sheet p. 59; cash flows p. 61 | O132: d45f8d1e0945df0b7b30254e96ff8c5dbd1df7d15b17c8ef7399c8e0206b7d7f
A133: Short-term borrowings and current maturities of long-term debt | B133: 1635000000 | D133: 2025-12-31T00:00:00.000Z | E133: 10-K | F133: 2026-02-12T00:00:00.000Z | G133: 0000059478-26-000013 | H133: us-gaap:DebtCurrent | I133: c-16 | J133: 6 | K133: -6 | L133: https://www.sec.gov/Archives/edgar/data/59478/000005947826000013/lly-20251231.htm | M133: 10-K balance sheet p. 59; cash flows p. 61 | O133: d45f8d1e0945df0b7b30254e96ff8c5dbd1df7d15b17c8ef7399c8e0206b7d7f
A134: Long-term debt | B134: 40868000000 | D134: 2025-12-31T00:00:00.000Z | E134: 10-K | F134: 2026-02-12T00:00:00.000Z | G134: 0000059478-26-000013 | H134: us-gaap:LongTermDebtNoncurrent | I134: c-16 | J134: 6 | K134: -6 | L134: https://www.sec.gov/Archives/edgar/data/59478/000005947826000013/lly-20251231.htm | M134: 10-K balance sheet p. 59; cash flows p. 61 | O134: d45f8d1e0945df0b7b30254e96ff8c5dbd1df7d15b17c8ef7399c8e0206b7d7f
A135: Operating cash flow · fiscal year | B135: 16813000000 | C135: 2025-01-01T00:00:00.000Z | D135: 2025-12-31T00:00:00.000Z | E135: 10-K | F135: 2026-02-12T00:00:00.000Z | G135: 0000059478-26-000013 | H135: us-gaap:NetCashProvidedByUsedInOperatingActivities | I135: c-1 | J135: 6 | K135: -6 | L135: https://www.sec.gov/Archives/edgar/data/59478/000005947826000013/lly-20251231.htm | M135: Annual cash-flow statement
...

Sheet About
A1: Topic | B1: Explanation | C1: Source
A2: Scope | B2: Lilly only. Balance-sheet facts checked October 14, 2026; financing and interest reviewed October 15; funding interpretation checked October 16. Financial statements dated June 30. Not investment advice. | C2: https://www.sec.gov/Archives/edgar/data/59478/000005947826000081/lly-20260630.htm
A3: Colors | B3: Arial 10. Full USD displayed in millions. Blue reported inputs, green cross-sheet links, black same-sheet calculations. Zero is a dash. Missing inputs are not zero.
A4: Cash generation | B4: Fiscal year + current YTD − prior YTD. Capital spending uses Lilly’s checked other-PP&E tag. FCF excludes acquisitions, dividends and other cash uses. | C4: https://github.com/jackconnolly1000-ux/sec-filing-research-terminal/blob/main/docs/pilot_cashflow_reconciliation.md
A5: Borrowing | B5: Balance-sheet current and noncurrent borrowing are added once. Fair-value table carrying amounts are not added again. | C5: https://github.com/jackconnolly1000-ux/sec-filing-research-terminal/blob/main/docs/pilot_evidence_lly.md
A6: Selected commitments | B6: Descriptions retain their disclosure dates; AtaiBeckley was disclosed after quarter end. They are not added to debt or to each other. | C6: https://www.sec.gov/Archives/edgar/data/59478/000005947826000081/lly-20260630.htm
A7: Dated review | B7: Repayment review uses exact H1 cash flows and historical annual carrying-debt buckets. Future coverage remains Unavailable. Text disclosures are identified separately; source hashes and dimensions are in Data. | C7: https://github.com/jackconnolly1000-ux/sec-filing-research-terminal/blob/main/docs/lly_liquidity_review.md
A8: Post-quarter events | B8: July acquisition cash is separate from June cash. The July $3.9B ceiling includes upfront cash. August $4.5B manufacturing announcement has no dated cash schedule. No overlap total inferred. | C8: https://www.sec.gov/Archives/edgar/data/59478/000005947826000077/q226lillysalesandearningsp.htm
A9: Financing inventory | B9: SEC index screened through October 15, 2026. May offering terms added as initial principal; full June debt schedule and drawable capacity remain Unavailable. | C9: https://data.sec.gov/submissions/CIK0000059478.json
A10: Contract evidence | B10: Series rates and maturities come from the final prospectus and certificates, corroborated by the completed offering. An 8-K coupon conflict is flagged; the corroborated 2029 fixed rate is 4.150%. | C10: https://github.com/jackconnolly1000-ux/sec-filing-research-terminal/blob/main/docs/lly_financing_audit.md
A11: Historical interest coverage | B11: Derived TTM operating income / reported interest expense. FY + current H1 − prior H1; each operating-income period reconciles to pretax less tagged nonoperating income (expense). | C11: https://github.com/jackconnolly1000-ux/sec-filing-research-terminal/blob/main/docs/lly_interest_coverage.md
A12: Capitalization basis | B12: FY2025 Note 11 explicitly reports interest on borrowings net of capitalized interest. The interim segment table labels the line interest expense without explicitly stating its capitalization basis. All three amounts are used as reported, before any interest-income offset. Capitalized interest is not added or subtracted; its amount and total interest incurred are Unavailable. | C12: FY2025 10-K Note 11 p. 77; June 10-Q Note 11 p. 23
A13: Ratio reconciliation | B13: Debt and liquidity shows current ratio, same-filing net debt, TTM OCF/debt and FCF/debt, and historical interest coverage. Denominator definitions and capital-spending bases differ by company. Values are historical, not future funding coverage. | C13: https://github.com/jackconnolly1000-ux/sec-filing-research-terminal/blob/main/docs/ratio_reconciliation.md
A14: Borrowing and leases | B14: The Borrowing and leases sheet reconciles baseline borrowing and shows lease balances on their own dates. Unavailable means the amount was not established in the checked evidence. Leases never enter baseline debt or its ratios. | C14: https://github.com/jackconnolly1000-ux/sec-filing-research-terminal/blob/main/docs/borrowing_lease_presentation.md
A15: History | B15: Two dated observations per company. Fiscal-year and TTM flows are overlapping twelve-month windows. Vistra FY2025 borrowing and dependent ratios use the checked annual financing line once. | C15: https://github.com/jackconnolly1000-ux/sec-filing-research-terminal/blob/main/docs/company_history.md
... A18: Annual history | B18: Annual cash and borrowing are fiscal-year-end balances. OCF and capital spending cover each full fiscal year. FCF = OCF − capital spending; it excludes acquisitions and other investing and financing uses. Historical amounts do not establish future repayment coverage. Fiscal calendars, business perimeters and capital-spending definitions differ. 2021/2022 cash flows use FY2023’s disclosed IPR&D milestone reclassification. OCF increased by $105.2M/$501.3M through classification, not new cash generation. Cash and borrowing retain their original balance sheets. FCF does not deduct IPR&D purchases. | C18: https://github.com/jackconnolly1000-ux/sec-filing-research-terminal/blob/main/docs/annual_history_reconciliation.md
